{
  "lastUpdate": "2025-12-02T17:46:28.082283Z",
  "news": {
    "Gaming": [
      {
        "title": "AN INNER WORLD [Free]",
        "link": "https://invideogames-jam.itch.io/an-inner-world",
        "description": "",
        "pubDate": "2025-12-02T17:36:06Z",
        "source": "invideogames-jam.itch.io",
        "image": "https://img.itch.zone/aW1nLzI0MzY1NDg0LnBuZw==/315x250%23c/ZmbiEb.png",
        "bias": 0
      },
      {
        "title": "Fablewood Burrow [Free] [Action] [Android]",
        "link": "https://dorohofer.itch.io/fablewood-burrow",
        "description": "",
        "pubDate": "2025-12-02T17:31:01Z",
        "source": "dorohofer.itch.io",
        "image": "https://img.itch.zone/aW1nLzI0MzY1Mzk3LmpwZw==/315x250%23c/N76Q6%2F.jpg",
        "bias": 0
      },
      {
        "title": "I Hear You [Free]",
        "link": "https://invideogames-jam.itch.io/i-hear-you",
        "description": "",
        "pubDate": "2025-12-02T17:28:08Z",
        "source": "invideogames-jam.itch.io",
        "image": "https://img.itch.zone/aW1nLzI0MzY1NDI2LnBuZw==/315x250%23c/Gb9ZE6.png",
        "bias": 0
      },
      {
        "title": "ErfCity 1.1 [$1.00] [Puzzle]",
        "link": "https://maxdemage.itch.io/erfcity",
        "description": "Build a thriving city in this minimalist puzzle game.",
        "pubDate": "2025-12-02T17:26:55Z",
        "source": "maxdemage.itch.io",
        "image": "https://img.itch.zone/aW1nLzI0MzY1MzM1LmpwZw==/315x250%23c/yVBHTG.jpg",
        "bias": 0
      },
      {
        "title": "IcePath [Free]",
        "link": "https://vaalmota.itch.io/icepath",
        "description": "Acompaña a dalila en la travesia de su vida (¡¿Literalmente?!)",
        "pubDate": "2025-12-02T17:23:07Z",
        "source": "vaalmota.itch.io",
        "image": "https://img.itch.zone/aW1nLzI0MzY1MDU4LnBuZw==/315x250%23c/7zY7oO.png",
        "bias": 0
      },
      {
        "title": "ANXIETY [Free]",
        "link": "https://invideogames-jam.itch.io/anxiety",
        "description": "",
        "pubDate": "2025-12-02T17:22:15Z",
        "source": "invideogames-jam.itch.io",
        "image": "https://img.itch.zone/aW1nLzI0MzY1MjkwLnBuZw==/315x250%23c/Sp%2B75U.png",
        "bias": 0
      },
      {
        "title": "99 NIGHTS IN THE FOREST REMAKED. TEST MODE [Free] [Action]",
        "link": "https://yoshi-to-be-charmander.itch.io/99-nights-in-the-forest-remaked-test-mode",
        "description": "",
        "pubDate": "2025-12-02T17:21:03Z",
        "source": "yoshi-to-be-charmander.itch.io",
        "image": "https://img.itch.zone/aW1nLzI0MzY1Mjg3LnBuZw==/315x250%23c/DzE7t1.png",
        "bias": 0
      },
      {
        "title": "Cohete Feli [Free] [Adventure] [Windows]",
        "link": "https://undying-spring20.itch.io/cohete-feli",
        "description": "",
        "pubDate": "2025-12-02T17:20:39Z",
        "source": "undying-spring20.itch.io",
        "image": "https://img.itch.zone/aW1nLzI0MzY1Mjc1LmpwZw==/315x250%23c/gvIWX8.jpg",
        "bias": 0
      },
      {
        "title": "Near Miss [$1.00] [Strategy]",
        "link": "https://bobtilian.itch.io/near-miss",
        "description": "Defend a pixel planet from pixel asteroids",
        "pubDate": "2025-12-02T17:20:16Z",
        "source": "bobtilian.itch.io",
        "image": "https://img.itch.zone/aW1nLzI0MzY1MzEwLnBuZw==/315x250%23c/YExfvZ.png",
        "bias": 0
      },
      {
        "title": "あなたと描く20日 [Free] [Visual Novel]",
        "link": "https://kurotya-969.itch.io/20",
        "description": "",
        "pubDate": "2025-12-02T17:19:46Z",
        "source": "kurotya-969.itch.io",
        "image": "https://img.itch.zone/aW1nLzI0MzY1MjY0LmpwZw==/315x250%23c/ZGxttv.jpg",
        "bias": 0
      },
      {
        "title": "Cohete [Free]",
        "link": "https://viri-oz.itch.io/cohete-22",
        "description": "Entrega la maruchan a el astronauta",
        "pubDate": "2025-12-02T17:17:53Z",
        "source": "viri-oz.itch.io",
        "image": "https://img.itch.zone/aW1nLzI0MzY1MjIzLnBuZw==/315x250%23c/jMKavl.png",
        "bias": 0
      },
      {
        "title": "Ashen Veil [Free] [Adventure]",
        "link": "https://saskia-gerdes.itch.io/ashen-veil",
        "description": "",
        "pubDate": "2025-12-02T17:17:29Z",
        "source": "saskia-gerdes.itch.io",
        "image": "https://img.itch.zone/aW1nLzI0MzY1MTc4LmpwZw==/315x250%23c/3GTYJ6.jpg",
        "bias": 0
      },
      {
        "title": "Monyo [Free] [Interactive Fiction]",
        "link": "https://sumiree1155.itch.io/monyo",
        "description": "A magical story where cats, secrets, and adventure await.",
        "pubDate": "2025-12-02T17:08:28Z",
        "source": "sumiree1155.itch.io",
        "image": "https://img.itch.zone/aW1nLzI0MzY0OTk4LnBuZw==/315x250%23c/zE1ab%2F.png",
        "bias": 0
      },
      {
        "title": "path of sorcerers [Free] [Shooter]",
        "link": "https://sdec-dev.itch.io/path-of-sorcerers",
        "description": "",
        "pubDate": "2025-12-02T17:00:51Z",
        "source": "sdec-dev.itch.io",
        "image": "https://img.itch.zone/aW1nLzI0MzY0OTQzLnBuZw==/315x250%23c/vZWO7U.png",
        "bias": 0
      },
      {
        "title": "Got That Dog In Me [Free] [Windows]",
        "link": "https://powderhound.itch.io/got-that-dog-in-me",
        "description": "",
        "pubDate": "2025-12-02T16:41:37Z",
        "source": "powderhound.itch.io",
        "image": "https://img.itch.zone/aW1nLzI0MzY0NjY3LnBuZw==/315x250%23c/Ci6QmP.png",
        "bias": 0
      },
      {
        "title": "Froggin Around [Free] [Puzzle]",
        "link": "https://itay4fom.itch.io/froggin-around",
        "description": "Froggin Around",
        "pubDate": "2025-12-02T16:29:15Z",
        "source": "itay4fom.itch.io",
        "image": "https://img.itch.zone/aW1nLzI0MzY1MzEyLnBuZw==/315x250%23c/%2Bp1V%2FA.png",
        "bias": 0
      },
      {
        "title": "Unofficial FSP Desktop Pets [Free] [Other] [Windows] [macOS]",
        "link": "https://roxfreeze.itch.io/desktoppets",
        "description": "A fan-made Desktop Pet featuring FSP mascots.",
        "pubDate": "2025-12-02T15:42:54Z",
        "source": "roxfreeze.itch.io",
        "image": "https://img.itch.zone/aW1nLzI0MzYzNjg1LnBuZw==/315x250%23c/wtLOVq.png",
        "bias": 0
      },
      {
        "title": "Sonic Ring Run - Godot Version [Free] [Other]",
        "link": "https://jslegend.itch.io/sonic-ring-run-godot-version",
        "description": "",
        "pubDate": "2025-12-02T00:38:42Z",
        "source": "jslegend.itch.io",
        "image": "https://img.itch.zone/aW1nLzI0MzY0NTYwLnBuZw==/315x250%23c/X5qwtv.png",
        "bias": 0
      }
    ],
    "World": [
      {
        "title": "Israeli forces kill two Palestinian teenagers in occupied West Bank",
        "link": "https://www.aljazeera.com/news/2025/12/2/israeli-forces-kill-two-palestinian-teenagers-in-occupied-west-bank?traffic_source=rss",
        "description": "An Israeli drone strike in Khan Younis, Gaza also killed photojournalist Mahmoud Wadi.",
        "pubDate": "2025-12-02T17:30:00Z",
        "source": "aljazeera.com",
        "image": "",
        "bias": -1
      },
      {
        "title": "Why is Trump threatening Venezuela's Maduro?",
        "link": "https://www.bbc.com/news/articles/c93n4nx5yqro?at_medium=RSS&at_campaign=rss",
        "description": "We look at what is behind the deployment of a large US military force to within striking distance of Venezuela.",
        "pubDate": "2025-12-02T17:06:32Z",
        "source": "bbc.com",
        "image": "https://ichef.bbci.co.uk/ace/standard/240/cpsprodpb/30f6/live/6751aa00-cf94-11f0-b259-a9faa8642480.jpg",
        "bias": 0
      },
      {
        "title": "Ex-EU top diplomat Mogherini detained in Belgium fraud case: Reports",
        "link": "https://www.aljazeera.com/news/2025/12/2/ex-eu-top-diplomat-mogherini-detained-in-belgium-fraud-case-reports?traffic_source=rss",
        "description": "Mogherini is reported to be among three in custody for suspected fraud involving an EU-funded training programme.",
        "pubDate": "2025-12-02T17:03:16Z",
        "source": "aljazeera.com",
        "image": "",
        "bias": -1
      },
      {
        "title": "Ukrainians in war-ravaged Donbas weigh prospects of peace deal",
        "link": "https://www.bbc.com/news/articles/cpq47derx2vo?at_medium=RSS&at_campaign=rss",
        "description": "While many Ukrainians believe they have sacrificed too much for their country to lose territory to Russia, others are desperate for the war to end.",
        "pubDate": "2025-12-02T17:00:23Z",
        "source": "bbc.com",
        "image": "https://ichef.bbci.co.uk/ace/standard/240/cpsprodpb/8ca2/live/3919b6d0-cf82-11f0-8c06-f5d460985095.jpg",
        "bias": 0
      },
      {
        "title": "LIVE: Barcelona vs Atletico Madrid – La Liga",
        "link": "https://www.aljazeera.com/sports/liveblog/2025/12/2/live-barcelona-vs-atletico-madrid-la-liga?traffic_source=rss",
        "description": "Follow the build-up, analysis and live text commentary of the game as Barcelona host fellow title contenders Atletico.",
        "pubDate": "2025-12-02T17:00:00Z",
        "source": "aljazeera.com",
        "image": "",
        "bias": -1
      },
      {
        "title": "Trump’s Military Moves & Claims on Venezuela",
        "link": "https://www.aljazeera.com/video/fact-check/2025/12/2/trumps-military-moves-claims-on-venezuela?traffic_source=rss",
        "description": "Conflicting US claims on Venezuela are escalating fast - from “closed” airspace to defending deadly vessel strikes.",
        "pubDate": "2025-12-02T16:57:25Z",
        "source": "aljazeera.com",
        "image": "",
        "bias": -1
      },
      {
        "title": "Propaganda or military victory? Russia claims capture of Pokrovsk",
        "link": "https://www.aljazeera.com/video/newsfeed/2025/12/2/propaganda-or-military-victory-russia-claims-capture-of-pokrovsk?traffic_source=rss",
        "description": "Russia claims to have captured the key eastern Ukrainian city of Pokrovsk, but is this a real victory or propaganda?",
        "pubDate": "2025-12-02T16:52:56Z",
        "source": "aljazeera.com",
        "image": "",
        "bias": -1
      },
      {
        "title": "Nigeria grants asylum to Guinea-Bissau presidential candidate after coup",
        "link": "https://www.bbc.com/news/articles/ce3wq2zznz1o?at_medium=RSS&at_campaign=rss",
        "description": "Nigeria says it is sheltering Fernando Dias in its embassy in Bissau, citing an imminent threat to his life.",
        "pubDate": "2025-12-02T16:51:10Z",
        "source": "bbc.com",
        "image": "https://ichef.bbci.co.uk/ace/standard/240/cpsprodpb/1f46/live/c8b41850-cf4e-11f0-be6b-6dbef7b78d52.jpg",
        "bias": 0
      },
      {
        "title": "Tennessee voters make final call in House special election testing Trump’s power - AP News",
        "link": "https://news.google.com/rss/articles/CBMirgFBVV95cUxPRElCWTZneER5LTBHN2RCWTR0VmpYdnQ2MDZySGt6clRhYmdwTUpCZzQ5T2w1cWdEOURxa05wVjdvSmlSckJnQWZBOTRUSTU0TGFGYlJSZmFia3dOZG04SUNMd0xHeU55ek1BR3pXYWp0OWpPUm1vSmlxMVdESm9fcjBpZW43SDJoOUl4TEp2aVVUMjRpc1IycUN0MERLRjhoN1RjWHA2X2V1cGhnTXc?oc=5",
        "description": "",
        "pubDate": "2025-12-02T16:51:00Z",
        "source": "news.google.com",
        "image": "",
        "bias": 0
      },
      {
        "title": "Officer recalls confronting Luigi Mangione during manhunt in UnitedHealthcare CEO shooting - AP News",
        "link": "https://news.google.com/rss/articles/CBMisgFBVV95cUxQVWtvYVprOHg3R3pNV3YyZ21jWXNLanVhRWlYMDQxeTh5ZERnSUJXWkVPXzJPMy1rNWVhR29jWmpSZTI3Y2hqR05OUld1dUtxMzV0RFR6c2c2eXd5bEtJVzR6cTJnSklMR29kb2ZBaTVLeEtBNTlvVjN4Sk9UOHNTSG9OaDN4Z0RfMTczWXlYUDFzQW13dnllX0lIeVZBSnN6VHhRZm1PUDh0RWNBNElSeTJ3?oc=5",
        "description": "",
        "pubDate": "2025-12-02T16:51:00Z",
        "source": "news.google.com",
        "image": "",
        "bias": 0
      },
      {
        "title": "Pope prays at Beirut port blast site on last day of Lebanon visit",
        "link": "https://www.bbc.com/news/articles/cn41jge1990o?at_medium=RSS&at_campaign=rss",
        "description": "Pope Leo XIV demanded justice for the more than 200 victims of the disaster, at the end of his three-day visit to Lebanon.",
        "pubDate": "2025-12-02T16:47:19Z",
        "source": "bbc.com",
        "image": "https://ichef.bbci.co.uk/ace/standard/240/cpsprodpb/423b/live/406c44d0-cf86-11f0-8c06-f5d460985095.jpg",
        "bias": 0
      },
      {
        "title": "Thousands of rounds of German army ammunition stolen from lorry",
        "link": "https://www.bbc.com/news/articles/c0q5n3x0jn9o?at_medium=RSS&at_campaign=rss",
        "description": "The theft reportedly took place after the driver left his truck in an unguarded parking lot overnight.",
        "pubDate": "2025-12-02T16:37:23Z",
        "source": "bbc.com",
        "image": "https://ichef.bbci.co.uk/ace/standard/240/cpsprodpb/22ea/live/25f36fc0-cf8b-11f0-9fb5-5f3a3703a365.jpg",
        "bias": 0
      },
      {
        "title": "Juan Orlando Hernandez freed after Trump’s ‘full and complete’ pardon",
        "link": "https://www.aljazeera.com/news/2025/12/2/juan-orlando-hernandez-freed-after-trumps-full-and-complete-pardon?traffic_source=rss",
        "description": "US President Trump defends the pardon, calling Hernandez's treatment 'harsh' and backing his political ally's party.",
        "pubDate": "2025-12-02T16:27:53Z",
        "source": "aljazeera.com",
        "image": "",
        "bias": -1
      },
      {
        "title": "Europe should seize Russia’s frozen assets now",
        "link": "https://www.aljazeera.com/opinions/2025/12/2/europe-should-seize-russias-frozen-assets-now?traffic_source=rss",
        "description": "With US aid stalled, only Moscow’s immobilised billions can keep Ukraine fighting.",
        "pubDate": "2025-12-02T15:48:17Z",
        "source": "aljazeera.com",
        "image": "",
        "bias": -1
      },
      {
        "title": "US Navy admiral ordered second  deadly Venezuela boat strike, White House says",
        "link": "https://www.bbc.com/news/articles/c0r95q9kv1go?at_medium=RSS&at_campaign=rss",
        "description": "The strikes, authorised by Defence Secretary Pete Hegseth, have raised fresh legality questions - but the White House says laws have been followed.",
        "pubDate": "2025-12-02T15:38:06Z",
        "source": "bbc.com",
        "image": "https://ichef.bbci.co.uk/ace/standard/240/cpsprodpb/6c32/live/36da48c0-cf6f-11f0-8c06-f5d460985095.jpg",
        "bias": 0
      },
      {
        "title": "Isack Hadjar to replace Yuki Tsunoda at Red Bull for 2026 F1 season",
        "link": "https://www.aljazeera.com/sports/2025/12/2/isack-hadjar-to-replace-yuki-tsunoda-at-red-bull-for-2026-f1-season?traffic_source=rss",
        "description": "Red Bull Racing will pair another new driver with Max Verstappen after Isack Hadjar replaced Yuki Tsunoda for next year.",
        "pubDate": "2025-12-02T15:31:53Z",
        "source": "aljazeera.com",
        "image": "",
        "bias": -1
      },
      {
        "title": "Is war between Ethiopia & Eritrea inevitable?: Mehdi Hasan & Getachew Reda",
        "link": "https://www.aljazeera.com/video/head-to-head/2025/12/2/is-war-between-ethiopia-eritrea-inevitable-mehdi-hasan-getachew-reda?traffic_source=rss",
        "description": "Mehdi Hasan debates Getachew Reda on his alliance with Prime Minister Abiy Ahmed and justice for the war in Tigray.",
        "pubDate": "2025-12-02T15:29:24Z",
        "source": "aljazeera.com",
        "image": "",
        "bias": -1
      },
      {
        "title": "Hadjar to partner Verstappen at Red Bull in 2026 as Tsunoda loses F1 seat - AP News",
        "link": "https://news.google.com/rss/articles/CBMijwFBVV95cUxQbFBvRGtOOEo2RjNCdkZsRnJtdHJHR0syTFlobUlJNE4xNFVxSHliWm1jR2Vld3VhNDZ6dHdqWkVKR1dDVGY0a0NsQVN1bEkzRm9aMDRFTTZXX3Q0WWlUNVd2MVJEQTJzdnhYbldRM0czZ2psXzZZR3NLeVd3WjNHYzA3d3JNX1NCOXc3SDlDaw?oc=5",
        "description": "",
        "pubDate": "2025-12-02T15:20:00Z",
        "source": "news.google.com",
        "image": "",
        "bias": 0
      },
      {
        "title": "Israel’s Netanyahu says deal with Syria possible but demands buffer zone",
        "link": "https://www.aljazeera.com/news/2025/12/2/israels-netanyahu-says-deal-with-syria-possible-but-demands-buffer-zone?traffic_source=rss",
        "description": "US is pushing for a non-aggression pact between Israel, Syria, but Netanyahu has shown little appetite for compromise.",
        "pubDate": "2025-12-02T15:18:31Z",
        "source": "aljazeera.com",
        "image": "",
        "bias": -1
      },
      {
        "title": "Athletic Bilbao vs Real Madrid La Liga preview – team news, start, lineups",
        "link": "https://www.aljazeera.com/sports/2025/12/2/athletic-bilbao-vs-real-madrid-la-liga-preview-team-news-start?traffic_source=rss",
        "description": "Madrid are in need of a win after a series of draws enabled rivals Barcelona to gain pole position in La Liga.",
        "pubDate": "2025-12-02T15:11:11Z",
        "source": "aljazeera.com",
        "image": "",
        "bias": -1
      },
      {
        "title": "Venezuela to continue accepting deported migrants despite Trump's airspace closure suggestion - AP News",
        "link": "https://news.google.com/rss/articles/CBMiqAFBVV95cUxOM0pIWXRKcFk5aFBqTWl6MXJldDczdEg5QzdlM0dEbFRiY21VUU90bmJiWlpIQUtISnpqS1NjUDZMWVdJNWdlZlhPdl85Y29ubExCcXAtT1VibUpZZDBONzQwMUpSWHB5TXBETm1YZHNvTk5iTHgwcTFvMDVPSVVyVGs5d0J0WnR5QkhLeXhSNGJReExSbE1hQWhGemkzQ2Q2QzY4dkMza1g?oc=5",
        "description": "",
        "pubDate": "2025-12-02T15:02:00Z",
        "source": "news.google.com",
        "image": "",
        "bias": 0
      },
      {
        "title": "Hillsborough investigation finds 12 police officers would have faced gross misconduct charges - AP News",
        "link": "https://news.google.com/rss/articles/CBMipAFBVV95cUxPVkpkdl9GelNTMFpObUtJNWJqUUhUeE1jTXhUblE2V3VZRHF3TmE5aW9GaE1vbVdESlcxUnc1c1l1d3FEbnlTU1hoX3g2MTV0RUw0MDdTZzl2NU5Kdjg4bUEtOVRvdklMWjFYNWlDejlIc2kwZ2pzNm94Y0VZS096MWNSX3Q5Wk1qbzU5M2laZVdnRTZPNEN1OWRUOVdfRllnRHp6Yg?oc=5",
        "description": "",
        "pubDate": "2025-12-02T15:01:00Z",
        "source": "news.google.com",
        "image": "",
        "bias": 0
      },
      {
        "title": "Zambian-American influencer sentenced to 18 months for hate speech",
        "link": "https://www.bbc.com/news/articles/cvgqnklqge7o?at_medium=RSS&at_campaign=rss",
        "description": "Known as \"One Boss Lady\",  Ethel Chisono Edwards has become known for her rants about the president.",
        "pubDate": "2025-12-02T14:58:51Z",
        "source": "bbc.com",
        "image": "https://ichef.bbci.co.uk/ace/standard/240/cpsprodpb/cd47/live/4a70de00-cf8b-11f0-8c06-f5d460985095.jpg",
        "bias": 0
      },
      {
        "title": "Bulgarian government pulls budget amid fierce protests",
        "link": "https://www.aljazeera.com/news/2025/12/2/bulgarian-government-pulls-budget-amid-fierce-protests?traffic_source=rss",
        "description": "Protesters argue the draft budget would increase taxes and inflation with little payoff, while entrenching corruption.",
        "pubDate": "2025-12-02T14:56:04Z",
        "source": "aljazeera.com",
        "image": "",
        "bias": -1
      },
      {
        "title": "Israel’s genocide in Gaza has not stopped, despite the ceasefire: Analysts",
        "link": "https://www.aljazeera.com/features/2025/12/2/israels-genocide-in-gaza-has-not-stopped-despite-ceasefire-analysts?traffic_source=rss",
        "description": "Analysts and a human rights group say Israel's genocide in Gaza has not stopped, despite the ceasefire.",
        "pubDate": "2025-12-02T14:48:12Z",
        "source": "aljazeera.com",
        "image": "",
        "bias": -1
      },
      {
        "title": "Was ex-Honduras leader Hernandez victim of Biden ‘set-up’, as Trump claims?",
        "link": "https://www.aljazeera.com/news/2025/12/2/was-ex-honduras-leader-hernandez-victim-of-biden-set-up-as-trump-claims?traffic_source=rss",
        "description": "Trump's plan to pardon ex-Honduran President Hernandez, convicted in a drug case, raises concerns over US credibility.",
        "pubDate": "2025-12-02T14:47:47Z",
        "source": "aljazeera.com",
        "image": "",
        "bias": -1
      },
      {
        "title": "Why is the UK scaling back jury trials, and why is it controversial?",
        "link": "https://www.aljazeera.com/news/2025/12/2/why-is-the-uk-scaling-back-jury-trials-and-why-is-it-controversial?traffic_source=rss",
        "description": "Right to trial by jury seen as a touchstone of the British justice system, but severe court backlogs may prompt change.",
        "pubDate": "2025-12-02T14:41:11Z",
        "source": "aljazeera.com",
        "image": "",
        "bias": -1
      },
      {
        "title": "Pope Leo wraps up his visit to Lebanon with prayers at the site of Beirut's port blast",
        "link": "https://www.npr.org/2025/12/02/g-s1-100056/pope-leo-lebanon-middle-east-visit-beirut-port",
        "description": "Pope Leo XIV ended his first overseas papal trip with prayers at Beirut's devastated port and a Mass attended by 150,000 worshippers in a country desperate for signs of hope amid fear of renewed war.",
        "pubDate": "2025-12-02T14:37:04Z",
        "source": "npr.org",
        "image": "",
        "bias": -1
      },
      {
        "title": "Scheffler returns at World Challenge and Rory McIlroy ends his year at the Australian Open - AP News",
        "link": "https://news.google.com/rss/articles/CBMisgFBVV95cUxOazU4RUc1bkdHZ3VTSzZFSHdLMlQwaUZNOVJzNHNTUHBRekFyd1k2b1FkWnJSeDB1ZXY2Y0dzNXhZU1kyNzN6SWswYmtVeWEyV2JteHNBT1hoRFlrMHpCMzBSdDVHbnVTQTZyYWdfMGV6THJ4b3YxM09iZDIxZ0UzNEhKZDVXWEg5NUVtd2RVMENDSEFrODhJdnR0X3luTXc4bjhqcVlZRHdRZW1kd3V5VU53?oc=5",
        "description": "",
        "pubDate": "2025-12-02T14:19:00Z",
        "source": "news.google.com",
        "image": "",
        "bias": 0
      },
      {
        "title": "Democrat Mandela Barnes, a former US Senate candidate, enters the Wisconsin governor's race - AP News",
        "link": "https://news.google.com/rss/articles/CBMipAFBVV95cUxNeFAwWTRCWU1xTzBjeXppd3ROTVpLZWcxcTJKUndwQjQxRU1oblRfcVpSSG50eWxNWkFnV2dCUFhpTmRnY3VELVNoOE9RbC1saFg0cWlmNnFXUV9UMGNzZVE2Y0xFX3o1QU1PWDZ6a3lneXE5dWp4eWNRbzItZ0xvQXlOa3psajh6aEFIZEpTYk11aGQ2S2ZkZWFkRl9zeXVZTG95aQ?oc=5",
        "description": "",
        "pubDate": "2025-12-02T14:12:00Z",
        "source": "news.google.com",
        "image": "",
        "bias": 0
      },
      {
        "title": "Afghanistan’s Taliban rulers carry out public execution in sports stadium in eastern city - AP News",
        "link": "https://news.google.com/rss/articles/CBMinAFBVV95cUxQQjNvbFdWSzNpYjVpbURKT3BYaF92ekE1cmpXbW5Ocm1KRjVrTjRqcmZVZTFRZjh6OUc1Rm50cFhBVVYwdG5YSTIwZkVYQ2dveWNoZTZMVFlZcnJ3cnZUZmVCZDNkam1UdGVJUzQ0VmZyUHMwdXdlQUhDYkJybUhJZHc4Y01kWlpXZWZsXzZ4ZE1YcDdMOHk3OXJOQzY?oc=5",
        "description": "",
        "pubDate": "2025-12-02T14:09:00Z",
        "source": "news.google.com",
        "image": "",
        "bias": 0
      },
      {
        "title": "Israel targeted Al Shifa Hospital “the same way” as military systems",
        "link": "https://www.aljazeera.com/video/quotable/2025/12/2/israel-targeted-al-shifa-hospital-the-same-way-as-military-systems?traffic_source=rss",
        "description": "\" What we are showing is the resilience, signs of resilience, trying to just stand up again.\"",
        "pubDate": "2025-12-02T14:01:42Z",
        "source": "aljazeera.com",
        "image": "",
        "bias": -1
      },
      {
        "title": "Live updates: Trump hosts Cabinet meeting amid scrutiny over boat strikes - AP News",
        "link": "https://news.google.com/rss/articles/CBMiY0FVX3lxTFBuNTM0X2RCSFJRcmx3VDkxaEYtSU0tUVVQZXlEN090aGZMZlJQR0dlWjBSQ1I1MnM5OWxPZk5XamgxWXhBdzJFTUZZOWNHRFFLQkJNR3hRSlFwZkF4S0hpMWROVQ?oc=5",
        "description": "",
        "pubDate": "2025-12-02T14:00:32Z",
        "source": "news.google.com",
        "image": "",
        "bias": 0
      },
      {
        "title": "Live updates: Putin accuses Europe of sabotaging peace efforts ahead of meeting with US envoy - AP News",
        "link": "https://news.google.com/rss/articles/CBMifEFVX3lxTE9DTVVnY1Z1X250TkhGcHh3SVdxZ2h3VVNTOU52QVYyWlU4YncydUpDN1hBTWYwd254dHRfY092Tm9tVzg3RWxBRzVTSmVPTG9oc0pXeGlTdk5oREJfOVZWTDQ1RHVZRmx0aGFLcl9YWDNQRHppNjZPN1M0VXA?oc=5",
        "description": "",
        "pubDate": "2025-12-02T14:00:32Z",
        "source": "news.google.com",
        "image": "",
        "bias": 0
      },
      {
        "title": "Trump’s boat bombings: How the US has long used ‘double-tap’ strikes",
        "link": "https://www.aljazeera.com/news/2025/12/2/trumps-boat-bombings-how-the-us-has-long-used-double-tap-strikes?traffic_source=rss",
        "description": "'Double strikes' allegedly used on Venezuelan boats accused of trafficking drugs were used extensively under Obama.",
        "pubDate": "2025-12-02T13:51:31Z",
        "source": "aljazeera.com",
        "image": "",
        "bias": -1
      },
      {
        "title": "Sudan’s paramilitary RSF claims control of key city of Babnusa",
        "link": "https://www.aljazeera.com/video/newsfeed/2025/12/2/sudans-paramilitary-rsf-claims-control-of-key-city-of-babnusa?traffic_source=rss",
        "description": "Sudan’s Rapid Support Forces say they have seized control of the city of Babnusa in West Kordofan.",
        "pubDate": "2025-12-02T13:44:10Z",
        "source": "aljazeera.com",
        "image": "",
        "bias": -1
      },
      {
        "title": "AI threatens to widen inequality among states: UN",
        "link": "https://www.aljazeera.com/news/2025/12/2/ai-threatens-to-widen-inequality-among-states-un?traffic_source=rss",
        "description": "Report warns of potential 'great divergence', with developed states profiting and others left behind.",
        "pubDate": "2025-12-02T13:18:17Z",
        "source": "aljazeera.com",
        "image": "",
        "bias": -1
      },
      {
        "title": "Is entertainment making us better or quietly reshaping us for the worse?",
        "link": "https://www.aljazeera.com/video/doha-debates/2025/12/2/is-entertainment-making-us-better-or-quietly-reshaping-us-for-the-worse?traffic_source=rss",
        "description": "Is this truly the golden age of creativity or has entertainment lost the meaning it once offered?",
        "pubDate": "2025-12-02T13:09:22Z",
        "source": "aljazeera.com",
        "image": "",
        "bias": -1
      },
      {
        "title": "Beyond Netanyahu: Israel’s major political corruption scandals",
        "link": "https://www.aljazeera.com/news/2025/12/2/beyond-netanyahu-israels-major-political-corruption-scandals?traffic_source=rss",
        "description": "Every prime minister in Tel Aviv since 1996 has been investigated on charges of corruption.",
        "pubDate": "2025-12-02T13:07:01Z",
        "source": "aljazeera.com",
        "image": "",
        "bias": -1
      },
      {
        "title": "Did ex-South African President Zuma’s daughter recruit for Russia’s war?",
        "link": "https://www.aljazeera.com/news/2025/12/2/did-ex-south-african-president-zumas-daughter-recruit-for-russias-war?traffic_source=rss",
        "description": "Duduzile Zuma-Sambudla is accused of luring men to Russia in the latest scandal rocking the prominent Zuma family.",
        "pubDate": "2025-12-02T13:06:18Z",
        "source": "aljazeera.com",
        "image": "",
        "bias": -1
      },
      {
        "title": "Hegseth under scrutiny after US kills boat strike survivors",
        "link": "https://www.aljazeera.com/video/newsfeed/2025/12/2/hegseth-under-scrutiny-after-us-kills-boat-strike-survivors?traffic_source=rss",
        "description": "US Secretary of War Pete Hegseth is facing questions after authorising a second attack on an alleged drug boat.",
        "pubDate": "2025-12-02T12:59:29Z",
        "source": "aljazeera.com",
        "image": "",
        "bias": -1
      },
      {
        "title": "Pope prays at site of 2020 Beirut port explosion",
        "link": "https://www.aljazeera.com/gallery/2025/12/2/pope-prays-at-site-of-2020-beirut-port-explosion?traffic_source=rss",
        "description": "Leo XIV urges justice and peace for Lebanon’s people as he wraps up his first foreign trip.",
        "pubDate": "2025-12-02T12:48:54Z",
        "source": "aljazeera.com",
        "image": "",
        "bias": -1
      },
      {
        "title": "National Guard attack suspect's crisis. And, U.S. official sheds light on boat strike",
        "link": "https://www.npr.org/2025/12/02/g-s1-99701/up-first-newsletter-venezuela-boat-strikes-national-guard-disabled-veteran-benefits",
        "description": "A U.S. official disputes the White House account of the deadly Caribbean boat strike. And, a person familiar with the National Guard shooting suspect says he was suffering a personal crisis.",
        "pubDate": "2025-12-02T12:45:46Z",
        "source": "npr.org",
        "image": "",
        "bias": -1
      },
      {
        "title": "Pope Leo wraps up Lebanon visit with prayers at site of Beirut port blast",
        "link": "https://www.aljazeera.com/news/2025/12/2/pope-leo-wraps-up-lebanon-visit-with-prayers-at-site-of-beirut-port-blast?traffic_source=rss",
        "description": "Capping off symbolic three-day visit, the Pontiff urged Lebanese unity and the pursuit of peace and justice.",
        "pubDate": "2025-12-02T12:40:14Z",
        "source": "aljazeera.com",
        "image": "",
        "bias": -1
      },
      {
        "title": "Bulgaria ditches budget plan after tens of thousands join protests",
        "link": "https://www.bbc.com/news/articles/cjezwzw088jo?at_medium=RSS&at_campaign=rss",
        "description": "Demonstrators said the plan - the country's first in euros - attempted to hide widespread government corruption.",
        "pubDate": "2025-12-02T12:04:00Z",
        "source": "bbc.com",
        "image": "https://ichef.bbci.co.uk/ace/standard/240/cpsprodpb/666d/live/99479cf0-cf61-11f0-902b-b378fe598ba1.jpg",
        "bias": 0
      },
      {
        "title": "Settler outposts spread among West Bank villages and fuel fear of more attacks - AP News",
        "link": "https://news.google.com/rss/articles/CBMiqgFBVV95cUxOczR4MEN2cU5COFgwblRlRmZidGZTeDBZbTZwdVVnaTFkUTJabTh4NEtBY0E4b1BVbFMxelhmU1dzTFcwb05MVHE4OGhmRzQ5ZFN3bDRqMmNGdDgzWk44c1BQR0oxS2MzcmVucWhUVGpxM18wWnVUaC1WaU5QNjJQYzM4dzlMekxwQm9yNl8zc0hfSnFuZ3ZRS08zSlljdm1jNVRHUjFkYXBvQQ?oc=5",
        "description": "",
        "pubDate": "2025-12-02T11:34:00Z",
        "source": "news.google.com",
        "image": "",
        "bias": 0
      },
      {
        "title": "World shares are mixed after a retreat on Wall Street - AP News",
        "link": "https://news.google.com/rss/articles/CBMiogFBVV95cUxPRXF0eGs4RzR4NkhDckZGV3BJYUVxLXNrQ0RDeXF6a2hNSUsyWU9zdzN4UWRfYU93STdiRU5WTmloQUZGR19udUp6cG1raUg3OEsycUVUUDFNdDBNTVhJMW50RXRqV2NaV1huXzREUEQzM1Fmdk5XbzE2Sk4wQ2dlTFpRcTUwV2FPXzhrVm5BYkNfck54Z1VHUUdNNV9aNkZad3c?oc=5",
        "description": "",
        "pubDate": "2025-12-02T10:57:00Z",
        "source": "news.google.com",
        "image": "",
        "bias": 0
      },
      {
        "title": "India tells smartphone makers to put state-run cyber safety app on new devices",
        "link": "https://www.bbc.com/news/articles/cedxyvx74p4o?at_medium=RSS&at_campaign=rss",
        "description": "India wants all smartphone makers to pre-install new devices with a state-owned cyber security app.",
        "pubDate": "2025-12-02T10:01:18Z",
        "source": "bbc.com",
        "image": "https://ichef.bbci.co.uk/ace/standard/240/cpsprodpb/90d2/live/51ed9140-cf37-11f0-a052-bdc1808acb03.jpg",
        "bias": 0
      },
      {
        "title": "'Hung by my wrists and beaten': Israeli-Russian woman says Iraqi militants tortured her in captivity",
        "link": "https://www.bbc.com/news/articles/cj69588eewyo?at_medium=RSS&at_campaign=rss",
        "description": "Elizabeth Tsurkov, who was freed in September, tells the BBC that her two years in captivity left her physically and mentally scarred.",
        "pubDate": "2025-12-02T09:53:16Z",
        "source": "bbc.com",
        "image": "https://ichef.bbci.co.uk/ace/standard/240/cpsprodpb/02a1/live/dc5d0c10-cc54-11f0-afd9-dfd0234147a3.jpg",
        "bias": 0
      },
      {
        "title": "Tip of an iceberg: Hong Kong’s deadly blaze raises anger over corruption and safety lapses - AP News",
        "link": "https://news.google.com/rss/articles/CBMiowFBVV95cUxNUEZncWVfTXlqYW1uNlZtQi1PbXNpaGJuVXp4V09Xb3pBcG9hdnIxY1RMMDlmR1ZVNGNxcW1tNktneEoxblpid0s3YTBlR2ZfODZKYjlvd28wQzVnZWptZDRoOHJtZjl0SWJhNDRmME8tMVd6WGlFbHotb2VZOWN6NXljRW1BMHVWckt5SWNTMGo4VkNPMGlBTlBVRTFqSDlJTGpj?oc=5",
        "description": "",
        "pubDate": "2025-12-02T09:49:00Z",
        "source": "news.google.com",
        "image": "",
        "bias": 0
      }
    ],
    "Politics": [
      {
        "title": "Plaid Cymru confirms budget talks with Welsh Labour",
        "link": "https://www.bbc.com/news/articles/c14vx501vvro?at_medium=RSS&at_campaign=rss",
        "description": "Talks focus on NHS and councils as Plaid says it is ready to get Wales out of a \"hole made by Labour\".",
        "pubDate": "2025-12-02T17:42:22Z",
        "source": "bbc.com",
        "image": "https://ichef.bbci.co.uk/ace/standard/240/cpsprodpb/5744/live/ccca6ca0-cf8a-11f0-8d79-4975c2144860.jpg",
        "bias": 0
      },
      {
        "title": "Ex-ballerina and former minister in race to be next Lord Speaker",
        "link": "https://www.bbc.com/news/articles/c1kp4ry0gkdo?at_medium=RSS&at_campaign=rss",
        "description": "Deborah Bull and Michael Forsyth are the two candidates standing to replace Lord McFall of Alcluith.",
        "pubDate": "2025-12-02T17:37:28Z",
        "source": "bbc.com",
        "image": "https://ichef.bbci.co.uk/ace/standard/240/cpsprodpb/3667/live/d1d077f0-cfa1-11f0-976e-4fc7ee951a33.jpg",
        "bias": 0
      },
      {
        "title": "Trump pardons Honduran ex-president who was convicted of drug crimes",
        "link": "https://www.npr.org/2025/12/02/nx-s1-5628382/trump-pardons-honduran-ex-president-juan-orlando-hernandez",
        "description": "President Trump has officially pardoned former Honduran President who US officials said was at the center of one of the largest and most violent drug-trafficking conspiracies in the world.",
        "pubDate": "2025-12-02T17:07:03Z",
        "source": "npr.org",
        "image": "",
        "bias": -1
      },
      {
        "title": "'Franklin' publisher slams Hegseth for his post of the turtle firing on drug boats",
        "link": "https://www.npr.org/2025/12/02/nx-s1-5628269/hegseth-boat-strikes-franklin-turtle",
        "description": "",
        "pubDate": "2025-12-02T16:57:03Z",
        "source": "npr.org",
        "image": "",
        "bias": -1
      },
      {
        "title": "Reeves speech did not mislead on challenges facing UK ahead of Budget, says OBR official",
        "link": "https://www.bbc.com/news/articles/czj0ngnkl2vo?at_medium=RSS&at_campaign=rss",
        "description": "Prof David Miles tells MPs the messaging given by the chancellor was \"not inconsistent\" with the situation she faced.",
        "pubDate": "2025-12-02T16:37:55Z",
        "source": "bbc.com",
        "image": "https://ichef.bbci.co.uk/ace/standard/240/cpsprodpb/7fe3/live/030ad020-cf7c-11f0-8390-cf8c18f355e0.jpg",
        "bias": 0
      },
      {
        "title": "Pope Leo XIV shares his thoughts on the conclave, reflects on spirituality and future travels - AP News",
        "link": "https://news.google.com/rss/articles/CBMiowFBVV95cUxNaXJucEl4SV9EUHl0SXdoT19jamg2bTUtSXhhbGhtakVfQkZPMllPaFJYYVNJVnBZbEJPQkw5aW1fRUx6c1JOYWxDc0tGV3FpNUF6N3FwTEt1LTRKZXBHUmUyZnZWTXM3TVdyS01qLU82M0IxRi1TdS1ocmV3X040M3FENEtQZ0ZiU25ZS183MGpDNGI0ZHgxT0tFMHR4UXNkMUZF?oc=5",
        "description": "",
        "pubDate": "2025-12-02T16:35:00Z",
        "source": "news.google.com",
        "image": "",
        "bias": 0
      },
      {
        "title": "Jury trials scrapped for crimes with sentences of less than three years",
        "link": "https://www.bbc.com/news/articles/cn5lxg2l0lqo?at_medium=RSS&at_campaign=rss",
        "description": "The reforms are being brought in to tackle unprecedented delays in the Crown Court.",
        "pubDate": "2025-12-02T16:08:38Z",
        "source": "bbc.com",
        "image": "https://ichef.bbci.co.uk/ace/standard/240/cpsprodpb/2e77/live/6f176b00-cf7e-11f0-8390-cf8c18f355e0.jpg",
        "bias": 0
      },
      {
        "title": "Ex-Reform MP Rupert Lowe sets up party",
        "link": "https://www.bbc.com/news/articles/c3r78zx271ro?at_medium=RSS&at_campaign=rss",
        "description": "Great Yarmouth First will represent needs of the town only, says founder Rupert Lowe.",
        "pubDate": "2025-12-02T15:45:21Z",
        "source": "bbc.com",
        "image": "https://ichef.bbci.co.uk/ace/standard/240/cpsprodpb/e4ad/live/7e0ed770-30ae-11f0-bb6f-6fd2e73bdb9e.jpg",
        "bias": 0
      },
      {
        "title": "UK criticises Gaza aid delays as tents take year to arrive",
        "link": "https://www.bbc.com/news/articles/cqlk663555no?at_medium=RSS&at_campaign=rss",
        "description": "Foreign Secretary Yvette Cooper said the situation remains \"dire\" as the United Nations warned 1.5 million people are in need of urgent shelter.",
        "pubDate": "2025-12-02T13:06:40Z",
        "source": "bbc.com",
        "image": "https://ichef.bbci.co.uk/ace/standard/240/cpsprodpb/442d/live/66641f80-cf01-11f0-bdb0-ab4ab31f90fa.png",
        "bias": 0
      },
      {
        "title": "Twelve more prisoners released in error, with two still missing, says Lammy",
        "link": "https://www.bbc.com/news/articles/c8e9py8g2yyo?at_medium=RSS&at_campaign=rss",
        "description": "The releases happened in the past three weeks, coming on top of 91 prisoners who were freed by mistake between April and October.",
        "pubDate": "2025-12-02T12:03:03Z",
        "source": "bbc.com",
        "image": "https://ichef.bbci.co.uk/ace/standard/240/cpsprodpb/d8b6/live/a83e0e40-cf5e-11f0-8c06-f5d460985095.png",
        "bias": 0
      },
      {
        "title": "Trump eyes next steps with Venezuela as lawmakers raise alarms about boat strikes",
        "link": "https://www.npr.org/2025/12/02/nx-s1-5627470/trump-eyes-next-steps-with-venezuela-as-lawmakers-raise-alarms-about-boat-strikes",
        "description": "President Trump met with his advisors Monday to discuss next steps with Venezuela as lawmakers continue to raise concerns about the administration's military strikes on boats in the Caribbean Sea.",
        "pubDate": "2025-12-02T11:47:00Z",
        "source": "npr.org",
        "image": "",
        "bias": -1
      },
      {
        "title": "In deep red Tennessee district, race for vacant congressional seat could be tight",
        "link": "https://www.npr.org/2025/12/02/nx-s1-5626883/in-deep-red-tennessee-district-race-for-vacant-congressional-seat-could-be-tight",
        "description": "Tennessee is a Republican stronghold, but the results of a special congressional election Tuesday will likely show whether Democrats can flip a seat held by the GOP for decades.",
        "pubDate": "2025-12-02T11:46:41Z",
        "source": "npr.org",
        "image": "",
        "bias": -1
      },
      {
        "title": "Democrats and Republicans are pouring money into a special election in Tennessee. Here's why",
        "link": "https://www.npr.org/2025/12/02/nx-s1-5626858/aftyn-behn-matt-van-epps-tennessee-special-election",
        "description": "Tuesday's special election for Tennessee's 7th Congressional District between Democrat Aftyn Behn and Republican Matt Van Epps has attracted outsize attention and spending from both parties.",
        "pubDate": "2025-12-02T10:00:00Z",
        "source": "npr.org",
        "image": "",
        "bias": -1
      },
      {
        "title": "Fox News faces critical test in 2nd case over false 2020 election claims",
        "link": "https://www.npr.org/2025/12/02/nx-s1-5627506/fox-news-smartmatic-lawsuit-election-claims-trial",
        "description": "",
        "pubDate": "2025-12-02T10:00:00Z",
        "source": "npr.org",
        "image": "",
        "bias": -1
      },
      {
        "title": "What scrapping the two-child benefit cap means",
        "link": "https://www.bbc.com/news/videos/c04vnd6gpd5o?at_medium=RSS&at_campaign=rss",
        "description": "Politics South reporter Emily Hudson explains the two-child benefit cap and why it was scrapped.",
        "pubDate": "2025-12-02T05:53:35Z",
        "source": "bbc.com",
        "image": "https://ichef.bbci.co.uk/ace/standard/240/cpsprodpb/c236/live/34697a70-ceac-11f0-9fb5-5f3a3703a365.jpg",
        "bias": 0
      },
      {
        "title": "Faisal Islam: OBR head's resignation leaves potential landmines for Reeves",
        "link": "https://www.bbc.com/news/articles/cwyvnnz5842o?at_medium=RSS&at_campaign=rss",
        "description": "Chancellor's next mission to find a respected and credible economist to run the OBR will require careful balance",
        "pubDate": "2025-12-02T00:29:54Z",
        "source": "bbc.com",
        "image": "https://ichef.bbci.co.uk/ace/standard/240/cpsprodpb/6724/live/0c29a230-cf4a-11f0-a892-01d657345866.jpg",
        "bias": 0
      }
    ],
    "Tech": [
      {
        "title": "Metroid Prime 4: Beyond is a technical marvel and game design nightmare",
        "link": "https://www.npr.org/2025/12/02/nx-s1-5627515/metroid-prime-4-beyond-review",
        "description": "After a decade of development, Metroid Prime 4: Beyond is a beautiful but befuddling game full of misguided design decisions and annoying sidekicks.",
        "pubDate": "2025-12-02T15:00:00Z",
        "source": "npr.org",
        "image": "",
        "bias": -1
      },
      {
        "title": "'First of its kind' scanner to study blast trauma",
        "link": "https://www.bbc.com/news/articles/c23e0k41kxeo?at_medium=RSS&at_campaign=rss",
        "description": "It will be able to monitor changes in brain function just minutes after weapon use, scientists say.",
        "pubDate": "2025-12-02T10:01:33Z",
        "source": "bbc.com",
        "image": "https://ichef.bbci.co.uk/ace/standard/240/cpsprodpb/56b2/live/e9fa9ff0-cec9-11f0-8741-59a8e037abac.jpg",
        "bias": 0
      },
      {
        "title": "AI’s impact could worsen gaps between world’s rich and poor, a UN report says - AP News",
        "link": "https://news.google.com/rss/articles/CBMiogFBVV95cUxQVGtxNUR3aEtGcWFyaUlicFlXYm96MU0wLXVMUE85ZnVreVlOWUl5ZjlWX1RtNDhsU1doTXF5OUlUeG1XYkJjbHRvbmQyVS1fS0p5bklvWXBQV2VXS0toVmJ3ZzBCQWdJcVIzV1RtQlI4ekwzdWdaZ21meEIyeEJxZW1qSnFGejU3NXc4c3ZCeWZGOFNxcmZ2YUp4S0lxX191eXc?oc=5",
        "description": "",
        "pubDate": "2025-12-02T08:57:00Z",
        "source": "news.google.com",
        "image": "",
        "bias": 0
      },
      {
        "title": "Fashion house Valentino criticised over 'disturbing' AI handbag ads",
        "link": "https://www.bbc.com/news/articles/cwyvjyvn83go?at_medium=RSS&at_campaign=rss",
        "description": "Social media users have called the luxury Italian fashion brand's artificial intelligence-made adverts \"cheap\" and \"lazy\".",
        "pubDate": "2025-12-02T08:26:01Z",
        "source": "bbc.com",
        "image": "https://ichef.bbci.co.uk/ace/standard/240/cpsprodpb/4e99/live/99bd24a0-cf6d-11f0-9128-0706b18c372a.jpg",
        "bias": 0
      },
      {
        "title": "Don't get angry, but the 2025 Oxford Word of the Year is 'rage bait'",
        "link": "https://www.npr.org/2025/12/01/nx-s1-5627179/rage-bait-oxford-word-of-the-year",
        "description": "The 2025 selection follows its predecessors, \"brain rot\" from 2024, \"rizz\" from 2023 and \"goblin mode\" from 2022.",
        "pubDate": "2025-12-02T00:07:24Z",
        "source": "npr.org",
        "image": "",
        "bias": -1
      }
    ],
    "Science": [
      {
        "title": "Mayor says too many families are 'working poor'",
        "link": "https://www.bbc.com/news/articles/c5y26k3dlp3o?at_medium=RSS&at_campaign=rss",
        "description": "Tracy Brabin talks to Radio Leeds about the Budget, COP30 and taxing tourists.",
        "pubDate": "2025-12-02T16:46:00Z",
        "source": "bbc.com",
        "image": "https://ichef.bbci.co.uk/ace/standard/240/cpsprodpb/6f7f/live/2a2b5e00-cf94-11f0-9fb5-5f3a3703a365.jpg",
        "bias": 0
      },
      {
        "title": "'Birdgirl' marks decade of making nature accessible",
        "link": "https://www.bbc.com/news/articles/c8r3k7rejp1o?at_medium=RSS&at_campaign=rss",
        "description": "Dr Mya-Rose Craig marks 10 years of Black2Nature and calls for wider access to nature across the UK.",
        "pubDate": "2025-12-02T06:16:55Z",
        "source": "bbc.com",
        "image": "https://ichef.bbci.co.uk/ace/standard/240/cpsprodpb/0afc/live/b9eb3600-cea9-11f0-83ff-5d092210839a.jpg",
        "bias": 0
      },
      {
        "title": "Why time is running out for Germany's green hydrogen industry",
        "link": "https://www.bbc.com/news/articles/cze60epnde0o?at_medium=RSS&at_campaign=rss",
        "description": "Firms are ready to make the equipment needed for green hydrogen, but demand has not picked up yet.",
        "pubDate": "2025-12-02T00:18:35Z",
        "source": "bbc.com",
        "image": "https://ichef.bbci.co.uk/ace/standard/240/cpsprodpb/63d1/live/54719ab0-bbc8-11f0-ae46-bd64331f0fd4.jpg",
        "bias": 0
      }
    ],
    "Business": [
      {
        "title": "Film producer Jason Blum and author-bookseller Ann Patchett to receive PEN America awards - AP News",
        "link": "https://news.google.com/rss/articles/CBMimwFBVV95cUxQVjNCb0trNUdaT1Z1R0FJLS1obWZLUWFLODRmTnVLZmQ1YmozMURXRlJCcTlmQjZnM3hKWjhxUGxwTEhpX0ZYT0xweGt2bzd3RkJhUjVfOWJnVUZUYXFNT2VndTJQRjdkUTRBa3o1Z1pGQmFwVVBxZUNiX3lPbVZPSWo3QkMtSVRqODhvYkxDVVU0dDIwcmxzMG5qSQ?oc=5",
        "description": "",
        "pubDate": "2025-12-02T15:53:00Z",
        "source": "news.google.com",
        "image": "",
        "bias": 0
      },
      {
        "title": "Jamie Laing's Candy Kittens to acquire UK snack brand Graze",
        "link": "https://www.bbc.com/news/articles/cp89j5dj95ro?at_medium=RSS&at_campaign=rss",
        "description": "The deal comes as Unilever plans to offload some food brands to focus on care and beauty.",
        "pubDate": "2025-12-02T12:37:42Z",
        "source": "bbc.com",
        "image": "https://ichef.bbci.co.uk/ace/standard/240/cpsprodpb/4393/live/df40bae0-cf50-11f0-8c06-f5d460985095.jpg",
        "bias": 0
      },
      {
        "title": "Bank of England warns of AI bubble risk",
        "link": "https://www.bbc.com/news/articles/cx2e0y3913jo?at_medium=RSS&at_campaign=rss",
        "description": "The central bank says US stock price valuations are their most stretched since the dotcom bubble burst.",
        "pubDate": "2025-12-02T12:11:17Z",
        "source": "bbc.com",
        "image": "https://ichef.bbci.co.uk/ace/standard/240/cpsprodpb/e7d3/live/82bf5640-cf56-11f0-902b-b378fe598ba1.jpg",
        "bias": 0
      },
      {
        "title": "Police consider corporate manslaughter charges in Post Office scandal",
        "link": "https://www.bbc.com/news/articles/c14vxlxv4kko?at_medium=RSS&at_campaign=rss",
        "description": "The move comes as police continue to investigate what has been called the UK's most widespread miscarriage of justice.",
        "pubDate": "2025-12-02T11:46:30Z",
        "source": "bbc.com",
        "image": "https://ichef.bbci.co.uk/ace/standard/240/cpsprodpb/ca6b/live/16c6efd0-cec9-11f0-81f3-a1b2f542a1e8.jpg",
        "bias": 0
      },
      {
        "title": "Bus ticket discount for city travel over Christmas",
        "link": "https://www.bbc.com/news/articles/cy95v5538w1o?at_medium=RSS&at_campaign=rss",
        "description": "The city council has discounted group tickets for bus travel across Hull over Christmas.",
        "pubDate": "2025-12-02T11:28:00Z",
        "source": "bbc.com",
        "image": "https://ichef.bbci.co.uk/ace/standard/240/cpsprodpb/d90b/live/cc76bf70-cf6b-11f0-996f-d5994b7e1100.jpg",
        "bias": 0
      },
      {
        "title": "Tax rises and tighter spending to hold back UK growth, OECD says",
        "link": "https://www.bbc.com/news/articles/cr5zdeyd1eeo?at_medium=RSS&at_campaign=rss",
        "description": "Growth in the UK economy is expected to slow next year, an influential global policy group predicts.",
        "pubDate": "2025-12-02T10:42:21Z",
        "source": "bbc.com",
        "image": "https://ichef.bbci.co.uk/ace/standard/240/cpsprodpb/c429/live/ddf7b190-cf7b-11f0-8c06-f5d460985095.jpg",
        "bias": 0
      },
      {
        "title": "Shein and Temu face calls for investigation over claims of stealing US designs",
        "link": "https://www.bbc.com/news/articles/c2lvzeyk21vo?at_medium=RSS&at_campaign=rss",
        "description": "Two senior US politicians accuse the platforms of malpractice, including intellectual property theft.",
        "pubDate": "2025-12-02T09:52:28Z",
        "source": "bbc.com",
        "image": "https://ichef.bbci.co.uk/ace/standard/240/cpsprodpb/d506/live/c8bf6b50-cf40-11f0-a875-abe379390415.jpg",
        "bias": 0
      },
      {
        "title": "Walmart leaving the New York Stock Exchange for NASDAQ in rebranding effort",
        "link": "https://www.npr.org/2025/12/02/nx-s1-5619786/walmart-leaving-the-new-york-stock-exchange-for-nasdaq-in-rebranding-effort",
        "description": "Walmart, the world's largest retailer, wants to be more of a tech company. So it's leaving the New York Stock Exchange and joining the NASDAQ.",
        "pubDate": "2025-12-02T09:44:00Z",
        "source": "npr.org",
        "image": "",
        "bias": -1
      },
      {
        "title": "Applications open for warm homes scheme help",
        "link": "https://www.bbc.com/news/articles/cg7v283p12no?at_medium=RSS&at_campaign=rss",
        "description": "The county council says the scheme provides free heating upgrades and prioritizes the most vulnerable.",
        "pubDate": "2025-12-02T06:49:25Z",
        "source": "bbc.com",
        "image": "https://ichef.bbci.co.uk/ace/standard/240/cpsprodpb/3813/live/19604d70-cecb-11f0-8741-59a8e037abac.jpg",
        "bias": 0
      },
      {
        "title": "Every pupil to get a hamper of gifts for Christmas",
        "link": "https://www.bbc.com/news/articles/c0jegjey1z3o?at_medium=RSS&at_campaign=rss",
        "description": "Headteacher Jade Hunter says she has not encountered generosity and goodwill like this before.",
        "pubDate": "2025-12-02T06:26:13Z",
        "source": "bbc.com",
        "image": "https://ichef.bbci.co.uk/ace/standard/240/cpsprodpb/e7ed/live/58397cc0-cecf-11f0-8c06-f5d460985095.png",
        "bias": 0
      },
      {
        "title": "Costco sues Trump administration for 'full refund' of tariffs",
        "link": "https://www.bbc.com/news/articles/c3r78peyzzlo?at_medium=RSS&at_campaign=rss",
        "description": "Two lower courts have already ruled against President Trump's use of emergency powers to impose tariffs.",
        "pubDate": "2025-12-02T03:40:49Z",
        "source": "bbc.com",
        "image": "https://ichef.bbci.co.uk/ace/standard/240/cpsprodpb/9918/live/775906d0-cf28-11f0-a810-c9f0bf5be1f8.jpg",
        "bias": 0
      },
      {
        "title": "Australia won't be intimidated by firms over social media ban, minister tells BBC",
        "link": "https://www.bbc.com/news/articles/cnv2z059745o?at_medium=RSS&at_campaign=rss",
        "description": "Anika Wells says she is ready to help nations which wish to copy Australia's social media ban for under-16s.",
        "pubDate": "2025-12-02T02:40:47Z",
        "source": "bbc.com",
        "image": "https://ichef.bbci.co.uk/ace/standard/240/cpsprodpb/7e5f/live/8ee0f950-cf2a-11f0-9fb5-5f3a3703a365.jpg",
        "bias": 0
      },
      {
        "title": "OBR head's resignation leaves potential landmines for Reeves",
        "link": "https://www.bbc.com/news/articles/cwyvnnz5842o?at_medium=RSS&at_campaign=rss",
        "description": "Chancellor's next mission to find a respected and credible economist to run the OBR will require careful balance",
        "pubDate": "2025-12-02T00:29:54Z",
        "source": "bbc.com",
        "image": "https://ichef.bbci.co.uk/ace/standard/240/cpsprodpb/6724/live/0c29a230-cf4a-11f0-a892-01d657345866.jpg",
        "bias": 0
      }
    ],
    "Culture": [
      {
        "title": "Diddy hits out at 'shameful' and 'illegal' documentary",
        "link": "https://www.bbc.com/news/articles/cm28ejzlv9lo?at_medium=RSS&at_campaign=rss",
        "description": "The rapper's representatives say the series is \"a shameful hit piece\" that \"relied on stolen footage\".",
        "pubDate": "2025-12-02T13:30:30Z",
        "source": "bbc.com",
        "image": "https://ichef.bbci.co.uk/ace/standard/240/cpsprodpb/cbc7/live/9134bb70-cf79-11f0-8390-cf8c18f355e0.jpg",
        "bias": 0
      },
      {
        "title": "Friends to leave Netflix in UK at the end of the year",
        "link": "https://www.bbc.com/news/articles/c8jwe311y37o?at_medium=RSS&at_campaign=rss",
        "description": "The comedy, which is one of the streamer's most popular shows, will leave the platform on 30 December.",
        "pubDate": "2025-12-02T12:07:22Z",
        "source": "bbc.com",
        "image": "https://ichef.bbci.co.uk/ace/standard/240/cpsprodpb/f83b/live/c9f10cb0-cf70-11f0-b355-05c29911d4af.jpg",
        "bias": 0
      },
      {
        "title": "'Scotland qualifying for the World Cup put me in hospital'",
        "link": "https://www.bbc.com/news/articles/c5yqpq7d844o?at_medium=RSS&at_campaign=rss",
        "description": "The BBC's entertainment correspondent Colin Paterson needed surgery after a mishap ahead of Scotland's World Cup qualifying game.",
        "pubDate": "2025-12-02T11:24:47Z",
        "source": "bbc.com",
        "image": "https://ichef.bbci.co.uk/ace/standard/240/cpsprodpb/c456/live/c0c324a0-cf90-11f0-8c06-f5d460985095.jpg",
        "bias": 0
      },
      {
        "title": "Iranian director given jail sentence while on trip to collect US awards",
        "link": "https://www.bbc.com/news/articles/c1m8e8l1mp2o?at_medium=RSS&at_campaign=rss",
        "description": "Jafar Panahi gets a one-year sentence in his absence for \"propaganda activities\" against the Iranian system.",
        "pubDate": "2025-12-02T10:40:12Z",
        "source": "bbc.com",
        "image": "https://ichef.bbci.co.uk/ace/standard/240/cpsprodpb/6822/live/59380c50-cf64-11f0-8351-b196ecbe551d.jpg",
        "bias": 0
      },
      {
        "title": "Car made famous by Bond was left to rust on a drive - now it's worth £1m",
        "link": "https://www.bbc.com/news/articles/c93w8xxj09jo?at_medium=RSS&at_campaign=rss",
        "description": "Local children jumped on the bonnet, and there was even a mouse nest in the highly-valuable car.",
        "pubDate": "2025-12-02T06:17:15Z",
        "source": "bbc.com",
        "image": "https://ichef.bbci.co.uk/ace/standard/240/cpsprodpb/50ce/live/cab641d0-cf0a-11f0-a892-01d657345866.jpg",
        "bias": 0
      },
      {
        "title": "Catherine asks for Cornish shanty in carol service",
        "link": "https://www.bbc.com/news/articles/cvgk75qzz0xo?at_medium=RSS&at_campaign=rss",
        "description": "The Princess of Wales asks Fisherman's Friends to sing a sea shanty in a royal Christmas service.",
        "pubDate": "2025-12-02T06:13:11Z",
        "source": "bbc.com",
        "image": "https://ichef.bbci.co.uk/ace/standard/240/cpsprodpb/c852/live/5582b960-cf4c-11f0-9c93-5b0bd9012bf1.jpg",
        "bias": 0
      },
      {
        "title": "Sound of 2026: 10 acts you'll be obsessed with next year",
        "link": "https://www.bbc.com/news/articles/c2dzx76gr3yo?at_medium=RSS&at_campaign=rss",
        "description": "The list tips new music for the coming year, following previous winners like Adele, Haim and Chappell Roan.",
        "pubDate": "2025-12-02T01:09:44Z",
        "source": "bbc.com",
        "image": "https://ichef.bbci.co.uk/ace/standard/240/cpsprodpb/1a11/live/3cea9d90-ced5-11f0-a892-01d657345866.png",
        "bias": 0
      }
    ]
  }
}