{
  "lastUpdate": "2025-09-19T02:46:05.896172Z",
  "news": {
    "Gaming": [
      {
        "title": "Pixel Snake+: Retro Arcade Reloaded [Free] [Puzzle]",
        "link": "https://xogost.itch.io/pixel-snake-retro-arcade-reloaded",
        "description": "Retro Snake reborn with power-ups, daily runs & flashy pixel vibes. Can you beat your best score?",
        "pubDate": "2025-09-19T01:53:51Z",
        "source": "xogost.itch.io",
        "image": "https://img.itch.zone/aW1nLzIzMjI0ODI4LnBuZw==/315x250%23c/9ekGQu.png",
        "bias": 0
      },
      {
        "title": "PARODYBOX SPRUNKI: Restarted (Early access) [Free] [Rhythm] [Windows] [macOS] [Linux] [Android]",
        "link": "https://nicolasgamer595.itch.io/parodybox-sprunki-restarted-early-access",
        "description": "Early access for Moch.",
        "pubDate": "2025-09-19T01:39:17Z",
        "source": "nicolasgamer595.itch.io",
        "image": "https://img.itch.zone/aW1nLzIzMjI0NjI1LmpwZw==/315x250%23c/IloO7d.jpg",
        "bias": 0
      },
      {
        "title": "Sprunki shifted but i remake some sprunkis [Free] [Windows] [macOS] [Linux] [Android]",
        "link": "https://tekch.itch.io/sprunki-shifted-but-i-remake-some-sprunkis",
        "description": "",
        "pubDate": "2025-09-19T01:38:37Z",
        "source": "tekch.itch.io",
        "image": "https://img.itch.zone/aW1nLzIzMjI0NjI2LnBuZw==/315x250%23c/MiEkx6.png",
        "bias": 0
      },
      {
        "title": "Asteroid Cleaner [Free] [Shooter]",
        "link": "https://eclipseandahalf.itch.io/asteroid-cleaner",
        "description": "A simple space shooter with a unique charging mechanic!",
        "pubDate": "2025-09-19T01:24:50Z",
        "source": "eclipseandahalf.itch.io",
        "image": "https://img.itch.zone/aW1nLzIzMjI0NTYzLnBuZw==/315x250%23c/7NvOJy.png",
        "bias": 0
      },
      {
        "title": "Arrow Escape [Free] [Platformer] [Windows]",
        "link": "https://migzss.itch.io/arrow-escape",
        "description": "Um marshmallow fofinho precisa desviar de armadilhas perigosas para alcançar o final da fase em segurança.",
        "pubDate": "2025-09-19T01:07:19Z",
        "source": "migzss.itch.io",
        "image": "https://img.itch.zone/aW1nLzIzMjI0OTg1LnBuZw==/315x250%23c/hlWR%2Fd.png",
        "bias": 0
      },
      {
        "title": "Marvel Super RPG [$4.00] [Role Playing] [Windows]",
        "link": "https://super-games-2025.itch.io/marvel-super-rpg",
        "description": "Marvel Super RPG",
        "pubDate": "2025-09-19T00:50:50Z",
        "source": "super-games-2025.itch.io",
        "image": "https://img.itch.zone/aW1nLzIzMjI0Mjg4LnBuZw==/315x250%23c/1cY80t.png",
        "bias": 0
      },
      {
        "title": "Of Coven and Weremoles [Free] [Adventure]",
        "link": "https://zombiemazter.itch.io/of-coven-and-weremoles",
        "description": "",
        "pubDate": "2025-09-19T00:50:15Z",
        "source": "zombiemazter.itch.io",
        "image": "https://img.itch.zone/aW1nLzIzMjI0NDM2LnBuZw==/315x250%23c/wVnCZX.png",
        "bias": 0
      },
      {
        "title": "Card Game (Pre-Release Demos) [Free] [Card Game] [Windows]",
        "link": "https://hekitsoftware.itch.io/cardgame",
        "description": "",
        "pubDate": "2025-09-19T00:48:15Z",
        "source": "hekitsoftware.itch.io",
        "image": "https://img.itch.zone/aW1nLzIzMjI0MTU4LmpwZw==/315x250%23c/1aACt2.jpg",
        "bias": 0
      },
      {
        "title": "Child's Play [Free] [Other]",
        "link": "https://ajgingercat.itch.io/childs-play",
        "description": "",
        "pubDate": "2025-09-19T00:46:59Z",
        "source": "ajgingercat.itch.io",
        "image": "https://img.itch.zone/aW1nLzIzMjI0MjMzLnBuZw==/315x250%23c/Cucwsf.png",
        "bias": 0
      },
      {
        "title": "u tag [Free] [Android]",
        "link": "https://nuh8y89h8h.itch.io/u-tag",
        "description": "",
        "pubDate": "2025-09-19T00:46:37Z",
        "source": "nuh8y89h8h.itch.io",
        "image": "https://img.itch.zone/aW1nLzIzMjI0MjI3LnBuZw==/315x250%23c/M8B%2Bsj.png",
        "bias": 0
      },
      {
        "title": "Harmless Drudge [Free] [Windows] [Linux]",
        "link": "https://qwtyest.itch.io/harmless-drudge",
        "description": "",
        "pubDate": "2025-09-19T00:45:35Z",
        "source": "qwtyest.itch.io",
        "image": "https://img.itch.zone/aW1nLzIzMjI0MjUwLnBuZw==/315x250%23c/qNVSID.png",
        "bias": 0
      },
      {
        "title": "Project Aghent [Free] [Adventure]",
        "link": "https://aghent.itch.io/project-aghent",
        "description": "",
        "pubDate": "2025-09-19T00:42:30Z",
        "source": "aghent.itch.io",
        "image": "https://img.itch.zone/aW1nLzIzMjI0MjU2LmpwZw==/315x250%23c/faPEDt.jpg",
        "bias": 0
      },
      {
        "title": "Gardens Of Lutonia [Free] [Adventure] [Windows]",
        "link": "https://snekjar.itch.io/lutonia",
        "description": "“Before Paris, before Lutetia…",
        "pubDate": "2025-09-19T00:33:32Z",
        "source": "snekjar.itch.io",
        "image": "https://img.itch.zone/aW1nLzIzMjI0MTQwLnBuZw==/315x250%23c/dvBqcY.png",
        "bias": 0
      },
      {
        "title": "Yarn Kitta (Pixelcram 2025) [Free] [Action]",
        "link": "https://technomantics.itch.io/yarn-kitta",
        "description": "1 button game to keep the string ball from the Yarn Kitta!",
        "pubDate": "2025-09-19T00:32:06Z",
        "source": "technomantics.itch.io",
        "image": "https://img.itch.zone/aW1nLzIzMjI0MDg5LnBuZw==/315x250%23c/fOGDCx.png",
        "bias": 0
      },
      {
        "title": "car taggers [Free] [Windows] [Android]",
        "link": "https://liamvr122.itch.io/car-taggers",
        "description": "",
        "pubDate": "2025-09-19T00:28:18Z",
        "source": "liamvr122.itch.io",
        "image": "https://img.itch.zone/aW1nLzIzMjI0MDMwLnBuZw==/315x250%23c/xCEUHZ.png",
        "bias": 0
      },
      {
        "title": "Classic Sudoku [Free] [Card Game]",
        "link": "https://fbeline.itch.io/classic-sudoku",
        "description": "Simple and relaxing classic Solitaire game",
        "pubDate": "2025-09-19T00:05:58Z",
        "source": "fbeline.itch.io",
        "image": "https://img.itch.zone/aW1nLzIzMjIzODA5LnBuZw==/315x250%23c/FDGw11.png",
        "bias": 0
      },
      {
        "title": "Fight-Knight [Free] [Survival] [Windows]",
        "link": "https://asteryng.itch.io/fight-knight",
        "description": "Fight off waves of increasingly difficult enemies to escape the evil kings arena.",
        "pubDate": "2025-09-19T00:01:47Z",
        "source": "asteryng.itch.io",
        "image": "https://img.itch.zone/aW1nLzIzMjIzOTQ0LnBuZw==/315x250%23c/YD%2F%2FZ6.png",
        "bias": 0
      }
    ],
    "World": [
      {
        "title": "Indonesian court sentences Ukrainian man to life for producing illegal drugs in Bali - AP News",
        "link": "https://news.google.com/rss/articles/CBMipAFBVV95cUxNaEZXcnY0ZVBiQWxiMVB6a0VpYUp5QjNiZU1lLVBKTHR5RXl1Tno1S0QzN0dVdnBRYklQTFU4OFBEaWVwNUdKb3VtYmdnd0xoVTJjYmNpWXd4VVI3S3AxU2Yzd1hldGRDeXJTSm0xNjI5LVozek9TakxCUFNRMUJteUhCUDBPLTZueHBSNHpadGlxVzJ3ZkpnakpsNC1Ddm9vV0dzZQ?oc=5",
        "description": "",
        "pubDate": "2025-09-19T02:36:00Z",
        "source": "news.google.com",
        "image": "",
        "bias": 0
      },
      {
        "title": "Magnitude 7.8 quake shakes Russia’s Far East region, prompts tsunami alert",
        "link": "https://www.aljazeera.com/news/2025/9/19/magnitude-7-8-quake-shakes-russias-far-east-region-prompts-tsunami-alert?traffic_source=rss",
        "description": "The US Geological Survey described the quake as an 'aftershock' from a massive magnitude 8.8 quake that struck in July.",
        "pubDate": "2025-09-19T02:05:32Z",
        "source": "aljazeera.com",
        "image": "",
        "bias": -1
      },
      {
        "title": "UK’s MI6 spy agency launches dark web portal, seeks out foreign spies",
        "link": "https://www.aljazeera.com/news/2025/9/19/uks-mi6-spy-agency-launches-dark-web-portal-seeks-out-foreign-spies?traffic_source=rss",
        "description": "Platform to allow people to securely pass on information anywhere in the world, or offer their own services to MI6.",
        "pubDate": "2025-09-19T01:47:27Z",
        "source": "aljazeera.com",
        "image": "",
        "bias": -1
      },
      {
        "title": "Leaders of Canada and Mexico vow closer economic ties in the face of Trump trade uncertainty - AP News",
        "link": "https://news.google.com/rss/articles/CBMinAFBVV95cUxNOEg2U1F0a1FQbTdUdEZWQTJ2bzlMMlo4bzhxQ1RHTkp0VTZuSTBYS2RLM3B3dk5jRVVua1dReXR5QWxXekhkb2ZtU0pKZVJRTVYwb2ptU0FsMWZkY1RXSUlwYkJ0eXF0Zl9QN19iVGhnX0wxRU1oLVNPbm83OTAyRHlCZjZER0lSSHBNbFdCamp3VGYzRGtTSmtIUmQ?oc=5",
        "description": "",
        "pubDate": "2025-09-19T01:33:00Z",
        "source": "news.google.com",
        "image": "",
        "bias": 0
      },
      {
        "title": "Clayton Kershaw to retire after 18 years with Dodgers and more than 3,000 strikeouts - AP News",
        "link": "https://news.google.com/rss/articles/CBMijAFBVV95cUxNajJEc0dwRXZXSXJtdlJjN3VDMnlWRjNSMkZZWnljdzVZZy1wa2VpVlpLV3lWdU1vLXFBbU9jek8zZGd5TUJCSTNDNlFpSi1QQzhrSmhXUy0tQU1qekh0RDY4TmlERWZpU2lwWTZfS0daYnlQWnFxT3JSQk9hNHBKbkxNdC1MWTdwWmFFVA?oc=5",
        "description": "",
        "pubDate": "2025-09-19T01:30:00Z",
        "source": "news.google.com",
        "image": "",
        "bias": 0
      },
      {
        "title": "Does painting cows with stripes prevent fly bites? Researchers who studied this wins Ig Nobel prize - AP News",
        "link": "https://news.google.com/rss/articles/CBMipwFBVV95cUxNaTVjcHZFY2w2SENJNllDX0ZJNzF2UmdGR0w2ZFNGQXdGQnBiNGxtdVVQYmtDeWZEUXpNZkpxbEtTU05BSFZCcGdyT0l6N1NpaUxtZ0dPOThxQnNWQkx3WGwwc1VPR3czZXIxTE1QaXQ1MEt0TXNoeHJaVWhUYktWOHlYWlJ1OWREdFBBbnRpUG01dEFOXzMtaDZUSE82U2MtVVU4dUhCZw?oc=5",
        "description": "",
        "pubDate": "2025-09-19T01:20:00Z",
        "source": "news.google.com",
        "image": "",
        "bias": 0
      },
      {
        "title": "Trump and Xi are set to discuss the TikTok deal and future of US-China relations - AP News",
        "link": "https://news.google.com/rss/articles/CBMimwFBVV95cUxQWll6dlc0MGtoM0ZBamNrQllRcUd1NzhaczVKb2NPcm0waXVNMS01U0RLUXpFVDFVcWhQWFlxSG1QajZJakVwbjg5VGN0a1gtbG9WenNpVlAyQXBIeWdhcUFEZ0RCUzBDYTdTOEtNMjdUSUNnUjRwbnhxQWJna1FVQ1lGT0ZENmxldEM1T2xjc3VyYW1KYTJIRFFmVQ?oc=5",
        "description": "",
        "pubDate": "2025-09-19T01:00:00Z",
        "source": "news.google.com",
        "image": "",
        "bias": 0
      },
      {
        "title": "Prosecutor says stalking suspect ambushed Pennsylvania police officers, killing 3 - AP News",
        "link": "https://news.google.com/rss/articles/CBMiqAFBVV95cUxQQjZJSXVPVmNwdHhEWE0xZnc5TVBMejFhZFAtMUw3VlhyemVfMTNWOTRINzhmVUM1U3RFYjJJMFhrRE0tQUxZNF9xb0F3d1ZzSlVOMFFyODZVdFhSR3ZpSENGWDctaHNlLXRXVmtNRVNNbjRydUkwTXlLRVVhUTUzVzlLTlUwem40TVR4NXlsSVZianlJYi1uOVRQSExRcWtYN2RzMzJWZzI?oc=5",
        "description": "",
        "pubDate": "2025-09-19T00:53:00Z",
        "source": "news.google.com",
        "image": "",
        "bias": 0
      },
      {
        "title": "AP Exclusive: Russia, Vietnam using energy profits to avoid possible US sanctions for arms deals - AP News",
        "link": "https://news.google.com/rss/articles/CBMiqwFBVV95cUxQaG5iU05rdm9HcGxyZ2pqUTVVbUplN1BpS0pXY1A2M1dfdm1HU19RX3NDR01sVXRNVEkydWxRRkdjMjlTUy0ybkpnbzZib3pqVTlMcXFmaWVQNjBmTHdOMzlqYkNoaDI4OFRDRUh0aTg0cEtkYXZSa25jVHNlekJibjFKTGthaU1udVRlbFZaNGV4TUEwdmJ5MXlaQlkwZ2g2NTRvVk1YQVRlems?oc=5",
        "description": "",
        "pubDate": "2025-09-19T00:49:00Z",
        "source": "news.google.com",
        "image": "",
        "bias": 0
      },
      {
        "title": "Trump says TV networks 'against' him should 'maybe' lose licence, after Kimmel suspension",
        "link": "https://www.bbc.com/news/articles/cr4qe0rz2zvo?at_medium=RSS&at_campaign=rss",
        "description": "His comments came as the head of the US broadcast regulator vowed to keep holding networks \"accountable\".",
        "pubDate": "2025-09-19T00:47:03Z",
        "source": "bbc.com",
        "image": "https://ichef.bbci.co.uk/ace/standard/240/cpsprodpb/bee1/live/71319a70-94d0-11f0-84c8-99de564f0440.jpg",
        "bias": 0
      },
      {
        "title": "Russia-Ukraine war: List of key events, day 1,303",
        "link": "https://www.aljazeera.com/news/2025/9/19/russia-ukraine-war-list-of-key-events-day-1303?traffic_source=rss",
        "description": "Here are the key events on day 1,303 of Russia’s war on Ukraine.",
        "pubDate": "2025-09-19T00:42:35Z",
        "source": "aljazeera.com",
        "image": "",
        "bias": -1
      },
      {
        "title": "Democrats introduce bill to protect free speech following Kimmel suspension - AP News",
        "link": "https://news.google.com/rss/articles/CBMia0FVX3lxTE9DbC1sVE5TcWZsTFdJOXl2TWo5SWVmVGVEVjkwMzlQLWVnMGNWYmkzSENFaF9ZcEVJbUFfOGJER1ItRFVKUjB4ZVFSdm1GMVdaUzhwaF9lYi03V1NTdFFkc2J6X0NJZExjWG1F?oc=5",
        "description": "",
        "pubDate": "2025-09-19T00:26:00Z",
        "source": "news.google.com",
        "image": "",
        "bias": 0
      }
    ],
    "Politics": [
      {
        "title": "Chris Mason: Delight and relief in government after state visit",
        "link": "https://www.bbc.com/news/articles/cvgn3445655o?at_medium=RSS&at_campaign=rss",
        "description": "Trump's disagreements with Sir Keir were somehow channelled past him, rather than at him, writes the BBC's political editor.",
        "pubDate": "2025-09-19T00:24:23Z",
        "source": "bbc.com",
        "image": "https://ichef.bbci.co.uk/ace/standard/240/cpsprodpb/e33b/live/8cb62fd0-94ef-11f0-9cf6-cbf3e73ce2b9.jpg",
        "bias": 0
      }
    ],
    "Tech": [],
    "Science": [],
    "Business": [
      {
        "title": "Canada and Mexico agree to deepen ties amid Trump trade war",
        "link": "https://www.bbc.com/news/articles/cwy8r042nx2o?at_medium=RSS&at_campaign=rss",
        "description": "The two also commit to a shared partnership with the US ahead of a review of a key North American free trade agreement.",
        "pubDate": "2025-09-19T01:38:44Z",
        "source": "bbc.com",
        "image": "https://ichef.bbci.co.uk/ace/standard/240/cpsprodpb/f645/live/b1093910-94f7-11f0-8431-a34ab217fb49.jpg",
        "bias": 0
      }
    ],
    "Culture": []
  }
}