{
  "lastUpdate": "2026-06-10T14:01:34.519616Z",
  "news": {
    "Gaming": [
      {
        "title": "KEEPALIVE Des [Free] [Survival] [Windows]",
        "link": "https://poredo.itch.io/keepalive-des",
        "description": "",
        "pubDate": "2026-06-10T13:51:35Z",
        "source": "poredo.itch.io",
        "image": "https://img.itch.zone/aW1nLzI3Nzg2OTczLmpwZw==/315x250%23c/eI0NBP.jpg",
        "bias": 0
      },
      {
        "title": "Until Dusk! DEMO [Free] [Shooter] [Windows]",
        "link": "https://arcane-focus-games.itch.io/until-dusk",
        "description": "A non-stop pressure cooker of zombie slaying fun!",
        "pubDate": "2026-06-10T13:45:50Z",
        "source": "arcane-focus-games.itch.io",
        "image": "https://img.itch.zone/aW1nLzI3Nzg2OTc4LmpwZw==/315x250%23c/S3GCo%2F.jpg",
        "bias": 0
      },
      {
        "title": "Star Squad [Free]",
        "link": "https://jo879344.itch.io/star-squad",
        "description": "",
        "pubDate": "2026-06-10T13:44:19Z",
        "source": "jo879344.itch.io",
        "image": "https://img.itch.zone/aW1nLzI3Nzg3MDA3LnBuZw==/315x250%23c/rL4Jsc.png",
        "bias": 0
      },
      {
        "title": "Beet`s Dilemma [Free] [Adventure] [Windows]",
        "link": "https://thepurplemoon.itch.io/beets-dilemma",
        "description": "Beet the Beetle has to make  a choice that makes or breaks the world. Literally.",
        "pubDate": "2026-06-10T13:40:07Z",
        "source": "thepurplemoon.itch.io",
        "image": "https://img.itch.zone/aW1nLzI3Nzg2OTIzLnBuZw==/315x250%23c/Mh687c.png",
        "bias": 0
      },
      {
        "title": "Ao oni 1.1 - FrenchDe [Free] [Action] [Android]",
        "link": "https://sionic22.itch.io/ao-oni-11-frenchde",
        "description": "",
        "pubDate": "2026-06-10T13:39:32Z",
        "source": "sionic22.itch.io",
        "image": "https://img.itch.zone/aW1nLzI3Nzg2OTA4LmpwZw==/315x250%23c/0sgwfV.jpg",
        "bias": 0
      },
      {
        "title": "Extreme Launcher [Free] [Adventure] [Windows]",
        "link": "https://coolgamerofports.itch.io/extreme-launcher",
        "description": "You can use either offline accounts or microsoft accounts.  Official Site and Credits: https://extremelauncher.net/",
        "pubDate": "2026-06-10T13:37:13Z",
        "source": "coolgamerofports.itch.io",
        "image": "https://img.itch.zone/aW1nLzI3Nzg2NzgxLmpwZw==/315x250%23c/13VtPr.jpg",
        "bias": 0
      },
      {
        "title": "The Drill [Free] [Other] [Windows]",
        "link": "https://seeb22.itch.io/the-drill",
        "description": "You are hired to remotely pilot a drill drone and descend ever deeper",
        "pubDate": "2026-06-10T13:35:23Z",
        "source": "seeb22.itch.io",
        "image": "https://img.itch.zone/aW1nLzI3Nzg2OTgyLnBuZw==/315x250%23c/3lmqBa.png",
        "bias": 0
      },
      {
        "title": "The Might Sloth VIZual Jam [Free] [Interactive Fiction] [Windows]",
        "link": "https://nigec.itch.io/the-might-sloth-vizual-jam",
        "description": "",
        "pubDate": "2026-06-10T13:35:14Z",
        "source": "nigec.itch.io",
        "image": "https://img.itch.zone/aW1nLzI3Nzg2Nzk3LnBuZw==/315x250%23c/FTOqJN.png",
        "bias": 0
      },
      {
        "title": "Untitled Roguelike [Free] [Action]",
        "link": "https://lolbrrrrrrb.itch.io/untitled-roguelike",
        "description": "",
        "pubDate": "2026-06-10T13:35:09Z",
        "source": "lolbrrrrrrb.itch.io",
        "image": "https://img.itch.zone/aW1nLzI3Nzg2Nzg3LnBuZw==/315x250%23c/QRc2jW.png",
        "bias": 0
      },
      {
        "title": "Ace Arena V1 [Free] [Simulation]",
        "link": "https://beboppp.itch.io/ace-arena-v1",
        "description": "Plane shooter prototype",
        "pubDate": "2026-06-10T13:32:21Z",
        "source": "beboppp.itch.io",
        "image": "https://img.itch.zone/aW1nLzI3Nzg2OTUzLnBuZw==/315x250%23c/dQQ7Kn.png",
        "bias": 0
      },
      {
        "title": "Splash Twist [Free]",
        "link": "https://emedjinee.itch.io/splash-twist",
        "description": "",
        "pubDate": "2026-06-10T13:28:56Z",
        "source": "emedjinee.itch.io",
        "image": "https://img.itch.zone/aW1nLzI3Nzg2ODI1LnBuZw==/315x250%23c/ADy0sY.png",
        "bias": 0
      },
      {
        "title": "Horizon Drift [Free] [Adventure]",
        "link": "https://misbahxhives.itch.io/horizon-drift",
        "description": "Every resource matters. Every decision counts. Find a way home.",
        "pubDate": "2026-06-10T13:26:58Z",
        "source": "misbahxhives.itch.io",
        "image": "https://img.itch.zone/aW1nLzI3Nzg2ODMxLnBuZw==/315x250%23c/WsQNUI.png",
        "bias": 0
      },
      {
        "title": "SUPER MAURO CROSS [Free] [Other] [Windows]",
        "link": "https://yuri7th.itch.io/super-mauro-cross",
        "description": "Atravesse a rua!",
        "pubDate": "2026-06-10T13:26:45Z",
        "source": "yuri7th.itch.io",
        "image": "https://img.itch.zone/aW1nLzI3Nzg2NjI1LnBuZw==/315x250%23c/vbVQy4.png",
        "bias": 0
      },
      {
        "title": "Code Rush learning code [Free] [Puzzle]",
        "link": "https://yminstudio.itch.io/code-rush",
        "description": "Learn to code, then prove your skills in PvP arena",
        "pubDate": "2026-06-10T13:24:10Z",
        "source": "yminstudio.itch.io",
        "image": "https://img.itch.zone/aW1nLzI3Nzg3MDI1LmpwZw==/315x250%23c/tVldrn.jpg",
        "bias": 0
      },
      {
        "title": "Awake [Free] [Fighting] [Windows]",
        "link": "https://mohdfayaz.itch.io/awake",
        "description": "Defend a sustainable energy battery from attacking wolves in an abandoned power plant.",
        "pubDate": "2026-06-10T13:16:48Z",
        "source": "mohdfayaz.itch.io",
        "image": "https://img.itch.zone/aW1nLzI3Nzg2NjUxLnBuZw==/315x250%23c/9ajM5m.png",
        "bias": 0
      },
      {
        "title": "Disc Align [Free] [Puzzle]",
        "link": "https://casual-garage-coder.itch.io/disc-align",
        "description": "Align the rings along the line as fast as possible",
        "pubDate": "2026-06-10T13:16:29Z",
        "source": "casual-garage-coder.itch.io",
        "image": "https://img.itch.zone/aW1nLzI3Nzg2NTEwLnBuZw==/315x250%23c/6ugOns.png",
        "bias": 0
      },
      {
        "title": "agapet [Free] [Interactive Fiction] [Windows]",
        "link": "https://teegk.itch.io/agapet",
        "description": "agapet",
        "pubDate": "2026-06-10T13:16:25Z",
        "source": "teegk.itch.io",
        "image": "https://img.itch.zone/aW1nLzI3Nzg2NjEwLmdpZg==/original/9hzAmf.gif",
        "bias": 0
      },
      {
        "title": "Steal in a minute [Free] [Windows]",
        "link": "https://a-games-studio.itch.io/steal-in-a-minute",
        "description": "",
        "pubDate": "2026-06-10T13:12:19Z",
        "source": "a-games-studio.itch.io",
        "image": "https://img.itch.zone/aW1nLzI3Nzg2NDU5LmpwZw==/315x250%23c/3SDboK.jpg",
        "bias": 0
      },
      {
        "title": "tuff aura [Free] [Platformer]",
        "link": "https://napoli115.itch.io/tuff-aura",
        "description": "",
        "pubDate": "2026-06-10T13:10:09Z",
        "source": "napoli115.itch.io",
        "image": "https://img.itch.zone/aW1nLzI3Nzg2NDY3LmpwZw==/315x250%23c/K1a6uG.jpg",
        "bias": 0
      },
      {
        "title": "Bounce Man [Free] [Platformer] [Windows]",
        "link": "https://masked-salad.itch.io/bounce-man",
        "description": "Jump Man got an upgrade...",
        "pubDate": "2026-06-10T13:07:58Z",
        "source": "masked-salad.itch.io",
        "image": "https://img.itch.zone/aW1nLzI3Nzg2NzIxLnBuZw==/315x250%23c/jqDw3o.png",
        "bias": 0
      },
      {
        "title": "GIF Works [Free]",
        "link": "https://fred-ponifasio.itch.io/gif-works",
        "description": "",
        "pubDate": "2026-06-10T13:06:01Z",
        "source": "fred-ponifasio.itch.io",
        "image": "https://img.itch.zone/aW1nLzI3Nzg2MzI1LmpwZw==/315x250%23c/cjUU%2Bz.jpg",
        "bias": 0
      },
      {
        "title": "Feed The Pit [Free] [Other]",
        "link": "https://mooncrustgames.itch.io/feed-the-pit",
        "description": "Feed it grain. Feed it goats. Feed it… whatever it asks for.",
        "pubDate": "2026-06-10T13:04:19Z",
        "source": "mooncrustgames.itch.io",
        "image": "https://img.itch.zone/aW1nLzI3Nzg2Njc3LmdpZg==/original/%2B6FXuE.gif",
        "bias": 0
      },
      {
        "title": "O espelho [Free] [Interactive Fiction]",
        "link": "https://melzinhaeagoat.itch.io/o-espelho",
        "description": "",
        "pubDate": "2026-06-10T13:01:55Z",
        "source": "melzinhaeagoat.itch.io",
        "image": "https://img.itch.zone/aW1nLzI3Nzg2Njg2LmpwZw==/315x250%23c/GhJynT.jpg",
        "bias": 0
      },
      {
        "title": "Expansion of unicorns [Free] [Strategy] [Windows] [Linux]",
        "link": "https://tav-developer.itch.io/unicorn-expansion",
        "description": "An open-source real-time strategy game about unicorns",
        "pubDate": "2026-06-10T13:00:20Z",
        "source": "tav-developer.itch.io",
        "image": "https://img.itch.zone/aW1nLzI3Nzg2MTEyLnBuZw==/315x250%23c/H2KXey.png",
        "bias": 0
      },
      {
        "title": "travel to europe ! [Free] [Educational]",
        "link": "https://puzzledlemur335.itch.io/travel-to-europe",
        "description": "",
        "pubDate": "2026-06-10T12:56:10Z",
        "source": "puzzledlemur335.itch.io",
        "image": "https://img.itch.zone/aW1nLzI3Nzg2NTIwLnBuZw==/315x250%23c/0dBWnG.png",
        "bias": 0
      },
      {
        "title": "Mou of Rage [Free] [Fighting]",
        "link": "https://iipsogames.itch.io/mou-of-rage",
        "description": "Beat 'em up de fútbol. Mourinho a puñetazos.",
        "pubDate": "2026-06-10T11:58:26Z",
        "source": "iipsogames.itch.io",
        "image": "https://img.itch.zone/aW1nLzI3Nzg2NjI5LnBuZw==/315x250%23c/3IJcZp.png",
        "bias": 0
      },
      {
        "title": "Campfire Keeper [Free]",
        "link": "https://vuthy.itch.io/campfire-keeper",
        "description": "",
        "pubDate": "2026-06-10T11:21:44Z",
        "source": "vuthy.itch.io",
        "image": "https://img.itch.zone/aW1nLzI3Nzg2NzE4LnBuZw==/315x250%23c/M5%2BPl5.png",
        "bias": 0
      },
      {
        "title": "Psycho Hunter! [$2.00] [Other]",
        "link": "https://spungulas.itch.io/psycho-hunter",
        "description": "A retro text based shooter/adventure/horror/comedy gore fest",
        "pubDate": "2026-06-10T10:39:42Z",
        "source": "spungulas.itch.io",
        "image": "https://img.itch.zone/aW1nLzI3Nzg2ODMzLmpwZw==/315x250%23c/WPk%2FJw.jpg",
        "bias": 0
      },
      {
        "title": "Brass Heart [Free] [Action] [Windows]",
        "link": "https://simenhs.itch.io/brass-heart",
        "description": "Deep sea submarine horror game",
        "pubDate": "2026-06-10T09:22:25Z",
        "source": "simenhs.itch.io",
        "image": "https://img.itch.zone/aW1nLzI3Nzg2MjE1LnBuZw==/315x250%23c/bRTgtT.png",
        "bias": 0
      }
    ],
    "World": [
      {
        "title": "Growing backlash in Japan over Trump's use of anime characters",
        "link": "https://www.bbc.com/news/articles/cdx7vynyl4eo?at_medium=RSS&at_campaign=rss",
        "description": "The US president has angered some fans by using the images of characters like Pikachu and Naruto.",
        "pubDate": "2026-06-10T13:42:23Z",
        "source": "bbc.com",
        "image": "https://ichef.bbci.co.uk/ace/standard/240/cpsprodpb/9b81/live/29004be0-64cb-11f1-8e1d-bbbb1017d210.jpg",
        "bias": 0
      },
      {
        "title": "Somali World Cup referee denied entry to US arrives home to hero’s welcome - AP News",
        "link": "https://news.google.com/rss/articles/CBMiowFBVV95cUxQc1ptcXN0N3JLa3Zuc1VPVWtmbnpab3RqRG01RUNtc1R5WmQ0R0tMY3hDMlE0WjQ5Y2owNHEzTUZ1M1luN3pxcDdlVERkbzFSTTJFbFlsVm5SWktCYTB1ZUxTak5zM0xaR0JYOFRxQ2RmYjNwck43WlVRSllDZXNkckVCU0NOcHc5LVVodF9fcWhKZU9vR2daUG8xZU5ZMFJWNTBB?oc=5",
        "description": "",
        "pubDate": "2026-06-10T13:39:00Z",
        "source": "news.google.com",
        "image": "",
        "bias": 0
      },
      {
        "title": "Eight red cards shown to Brazil in fiery friendly against US women",
        "link": "https://www.aljazeera.com/sports/2026/6/10/eight-red-cards-shown-to-brazil-in-fiery-friendly-against-us-women?traffic_source=rss",
        "description": "Four Brazilian players and four members of their coaching staff were sent off during a dramatic encounter in Fortaleza.",
        "pubDate": "2026-06-10T13:36:58Z",
        "source": "aljazeera.com",
        "image": "",
        "bias": -1
      },
      {
        "title": "US bombs Iran’s water facilities: Why that’s so significant",
        "link": "https://www.aljazeera.com/news/2026/6/10/us-bombs-irans-water-facilities-why-thats-so-significant?traffic_source=rss",
        "description": "The US struck several sites in Iran, saying it retaliated against the downing of a US helicopter in the Strait of Hormuz",
        "pubDate": "2026-06-10T13:27:27Z",
        "source": "aljazeera.com",
        "image": "",
        "bias": -1
      },
      {
        "title": "Trump and Iran trade new threats after strikes exchanged",
        "link": "https://www.bbc.com/news/articles/ce371kw2ex2o?at_medium=RSS&at_campaign=rss",
        "description": "The US president warns Iran \"will have to pay the price\" for taking too long to agree a deal, after Tehran vows retaliation to any attacks.",
        "pubDate": "2026-06-10T13:19:02Z",
        "source": "bbc.com",
        "image": "https://ichef.bbci.co.uk/ace/standard/240/cpsprodpb/127b/live/d754c2e0-64c4-11f1-8f51-b550443b533b.jpg",
        "bias": 0
      },
      {
        "title": "Mexico vs South Africa: World Cup 2026 opening game – teams, start, lineups",
        "link": "https://www.aljazeera.com/sports/2026/6/10/mexico-south-africa-fifa-world-cup-2026-match-lineup-players-news-football?traffic_source=rss",
        "description": "As the tournament kicks off, cohosts Mexico face South Africa in a replay of the 2010 edition's opening game.",
        "pubDate": "2026-06-10T13:06:47Z",
        "source": "aljazeera.com",
        "image": "",
        "bias": -1
      },
      {
        "title": "First charges laid over deadly Hong Kong fire",
        "link": "https://www.bbc.com/news/articles/c04yldyezyeo?at_medium=RSS&at_campaign=rss",
        "description": "The Wang Fuk Court blaze last year was the deadliest that Hong Kong had seen in 70 years, killing 168 people.",
        "pubDate": "2026-06-10T13:05:34Z",
        "source": "bbc.com",
        "image": "https://ichef.bbci.co.uk/ace/standard/240/cpsprodpb/b592/live/64617a00-64a4-11f1-9c89-85486d952f7c.jpg",
        "bias": 0
      },
      {
        "title": "West Bank ethnic cleansing, settler attacks Israel’s state policy: Amnesty",
        "link": "https://www.aljazeera.com/news/2026/6/10/west-bank-ethnic-cleansing-settler-attacks-israels-state-policy-amnesty?traffic_source=rss",
        "description": "Israel uses war crimes to accelerate 'annexation agenda and settlement expansion' in occupied land, rights group says.",
        "pubDate": "2026-06-10T12:55:23Z",
        "source": "aljazeera.com",
        "image": "",
        "bias": -1
      },
      {
        "title": "What to know about the World Cup referee from Somalia who was denied entry to the US - AP News",
        "link": "https://news.google.com/rss/articles/CBMioAFBVV95cUxQYUZ2dnlYc2p0RkphQU45Z1FkTUVHcWlZUVZVNTB1MjZxM1F2VkN5WUVuSVFoMDIwYklETzVKWEJlZ3Qxb2hfLWFGamxvYXJPdUdWZEZPaExFakFnT3lZbmw3UGtjMmdnN0Y5bzVPVk9JcmZCZWcxRzZxbHJBSUh3V2FxTUoza0d6WWNjSzlPLS1XLU1pemFkQjJyTTEyczJa?oc=5",
        "description": "",
        "pubDate": "2026-06-10T12:55:00Z",
        "source": "news.google.com",
        "image": "",
        "bias": 0
      },
      {
        "title": "7-month-old baby shot by Israeli soldier in Hebron",
        "link": "https://www.aljazeera.com/video/newsfeed/2026/6/10/7-month-old-baby-shot-by-israeli-soldier-in-hebron?traffic_source=rss",
        "description": "An Israeli soldier fired at a Palestinian family’s car in Hebron, fatally shooting a seven‑month‑old in the head.",
        "pubDate": "2026-06-10T12:44:39Z",
        "source": "aljazeera.com",
        "image": "",
        "bias": -1
      },
      {
        "title": "Ukraine-made ‘Flamingo’ missile hits target 900 km inside Russia",
        "link": "https://www.aljazeera.com/video/newsfeed/2026/6/10/ukraine-made-flamingo-missile-hits-target-900-km-inside-russia?traffic_source=rss",
        "description": "Video shows a Ukrainian-made ‘FP-5 Flamingo’ cruise missile flying deep inside Russia.",
        "pubDate": "2026-06-10T12:44:09Z",
        "source": "aljazeera.com",
        "image": "",
        "bias": -1
      },
      {
        "title": "Air India crash pilot's father vows to defend son's reputation",
        "link": "https://www.bbc.com/news/articles/cj0gj911060o?at_medium=RSS&at_campaign=rss",
        "description": "Investigators are expected to soon release an update on the crash, which killed 260 people last year.",
        "pubDate": "2026-06-10T12:37:19Z",
        "source": "bbc.com",
        "image": "https://ichef.bbci.co.uk/ace/standard/240/cpsprodpb/5bea/live/da3ed330-64b3-11f1-a758-750f2ac1a6ce.jpg",
        "bias": 0
      },
      {
        "title": "Hong Kong charges 7 people and 2 firms over massive fire that killed 168 - AP News",
        "link": "https://news.google.com/rss/articles/CBMimwFBVV95cUxQYlNNcmFXdFBWeHdQVXl1bkI1clFBSTRudmlScG5JTkRRbzZmSmVhRUY4RFM2ZGNOS0xNb1pOa1lwSnYydHRBR2tJeFhuR1BZZnRaNWdvVzhHQ3FUU2xqWkxzZlg4ZE5FVTVTV2pWZlJoTmE4YUtzV1Z3RzN3WVJnNUQyU3FCU1hUYzVoeHdlbGMwTk93aFl3VG5Ddw?oc=5",
        "description": "",
        "pubDate": "2026-06-10T12:34:00Z",
        "source": "news.google.com",
        "image": "",
        "bias": 0
      },
      {
        "title": "Pakistan military helicopter crashes in Kashmir, all on board killed",
        "link": "https://www.aljazeera.com/news/2026/6/10/pakistan-military-helicopter-crashes-in-kashmir-all-on-board-killed?traffic_source=rss",
        "description": "There has been a heavy security presence in Muzaffarabad amid protests in Pakistan-administered Kashmir in recent days.",
        "pubDate": "2026-06-10T12:30:19Z",
        "source": "aljazeera.com",
        "image": "",
        "bias": -1
      },
      {
        "title": "Kashmiri rights activist wins partial court victory but remains behind bars",
        "link": "https://www.aljazeera.com/news/2026/6/10/kashmiri-rights-activist-wins-partial-court-victory-but-remains-behind-bars?traffic_source=rss",
        "description": "The Delhi High Court grants bail to Kashmiri rights activist Khurram Parvez, jailed in India for nearly five years.",
        "pubDate": "2026-06-10T12:18:41Z",
        "source": "aljazeera.com",
        "image": "",
        "bias": -1
      },
      {
        "title": "Hero’s welcome for Somali referee denied entry to US World Cup tournament",
        "link": "https://www.aljazeera.com/news/2026/6/10/heros-welcome-for-somali-referee-denied-entry-to-us-world-cup-tournament?traffic_source=rss",
        "description": "The first Somali picked to referee a World Cup rose from Mogadishu's pitches, only to be barred at the US border.",
        "pubDate": "2026-06-10T12:15:48Z",
        "source": "aljazeera.com",
        "image": "",
        "bias": -1
      },
      {
        "title": "Netanyahu caught between the US, Lebanon war, and Iran ceasefire",
        "link": "https://www.aljazeera.com/news/2026/6/10/netanyahu-caught-between-the-us-lebanon-war-and-iran-ceasefire?traffic_source=rss",
        "description": "As elections near, Israel's PM finds himself squeezed between his voters, his allies, and his opponents.",
        "pubDate": "2026-06-10T11:57:49Z",
        "source": "aljazeera.com",
        "image": "",
        "bias": -1
      },
      {
        "title": "Apache down, fighting up: What the latest US-Iran attacks mean",
        "link": "https://www.aljazeera.com/news/2026/6/10/apache-down-fighting-up-what-the-latest-us-iran-attacks-mean?traffic_source=rss",
        "description": "Analysts say Iran seeks to deter US patrols on the Strait of Hormuz by attacking its assets across the Gulf.",
        "pubDate": "2026-06-10T11:50:48Z",
        "source": "aljazeera.com",
        "image": "",
        "bias": -1
      },
      {
        "title": "Satellite images show Israel’s destruction of historical city of Tyre",
        "link": "https://www.aljazeera.com/news/2026/6/10/satellite-images-show-israels-destruction-of-historical-city-of-tyre?traffic_source=rss",
        "description": "Satellite data shows damage to residential areas, UNESCO Heritage buffer zones and Palestinian camps in Israeli attacks.",
        "pubDate": "2026-06-10T11:46:50Z",
        "source": "aljazeera.com",
        "image": "",
        "bias": -1
      },
      {
        "title": "Ukraine says missiles hit military plant deep inside Russia",
        "link": "https://www.bbc.com/news/articles/c5yzm2nzgr2o?at_medium=RSS&at_campaign=rss",
        "description": "Ukraine's military also says it has struck a Russian oil refinery and a \"shadow fleet\" oil tanker in the Black Sea.",
        "pubDate": "2026-06-10T11:43:40Z",
        "source": "bbc.com",
        "image": "https://ichef.bbci.co.uk/ace/standard/240/cpsprodpb/3289/live/594e29c0-64bc-11f1-8f51-b550443b533b.png",
        "bias": 0
      },
      {
        "title": "What’s happening at the World Cup one day before tournament starts?",
        "link": "https://www.aljazeera.com/sports/2026/6/10/whats-happening-at-the-world-cup-one-day-before-tournament-starts?traffic_source=rss",
        "description": "Political issues continue to dominate the build-up, with the US-Israel war on Iran overshadowing the World Cup.",
        "pubDate": "2026-06-10T11:40:15Z",
        "source": "aljazeera.com",
        "image": "",
        "bias": -1
      },
      {
        "title": "U.S. and Iran exchange strikes. And, House passes ICE and Border Patrol funding",
        "link": "https://www.npr.org/2026/06/10/g-s1-127216/up-first-newsletter-iran-us-war-primary-results-ice-funding-bill-gates",
        "description": "The U.S. and Iran have exchanged strikes after a helicopter was downed Monday near the Strait of Hormuz. And, House Republicans have passed a bill to fund ICE and Border Patrol through Trump's term.",
        "pubDate": "2026-06-10T11:26:08Z",
        "source": "npr.org",
        "image": "",
        "bias": -1
      },
      {
        "title": "Why has Belfast erupted in anti-immigrant violence after a knife attack?",
        "link": "https://www.aljazeera.com/news/2026/6/10/why-has-belfast-erupted-in-anti-immigrant-violence-after-a-knife-attack?traffic_source=rss",
        "description": "Ministers have blamed far-right online agitators for stoking racial tension following a stabbing.",
        "pubDate": "2026-06-10T10:50:22Z",
        "source": "aljazeera.com",
        "image": "",
        "bias": -1
      },
      {
        "title": "Insider tour of the Sagrada Familia reveals 5 divine enigmas and hidden treasures - AP News",
        "link": "https://news.google.com/rss/articles/CBMiswFBVV95cUxOcmVoV0o0TlkxU05aMTFkVmliY3M3VTdzQWNuakVNUGFIQ3ZfQm1tRnM1OHRjaXptMHJuTm82SUJGSDdNalQ3THZ0X2xLWXBWeFVIcGpPdVJFSFlJVEtWVDZIbkpLQWdhWlQ5b0xNS0NNQ3FQaVJBVWdPVDNSNHptRmRNdFhDcjZPenU5WGdsVWwtZlNiUVdha0UxRW5FaXFBSmUwZVA4eXB0Wm51Y2k5TFZSYw?oc=5",
        "description": "",
        "pubDate": "2026-06-10T10:37:00Z",
        "source": "news.google.com",
        "image": "",
        "bias": 0
      },
      {
        "title": "China re‑centers North Korea ties as nuclear silence reshapes balance",
        "link": "https://www.npr.org/2026/06/10/g-s1-127013/xi-jinping-visits-pyongyang-china-north-korea-ties",
        "description": "Xi's silence on North Korea's nuclear program came as Kim tried to convince the world of the irreversibility of his country's status as a nuclear power.",
        "pubDate": "2026-06-10T10:30:00Z",
        "source": "npr.org",
        "image": "",
        "bias": -1
      },
      {
        "title": "Manhunt under way in South Africa after 12 killed in mass shooting in Johannesburg",
        "link": "https://www.bbc.com/news/articles/c79yzqw0z0wo?at_medium=RSS&at_campaign=rss",
        "description": "Another nine people were injured at an informal settlement in Cleveland late on Tuesday.",
        "pubDate": "2026-06-10T10:26:54Z",
        "source": "bbc.com",
        "image": "https://ichef.bbci.co.uk/ace/standard/240/cpsprodpb/d49f/live/4d102e40-64aa-11f1-b1db-af71d47507d6.jpg",
        "bias": 0
      },
      {
        "title": "Pakistan launches deadly air strikes in Afghanistan, reigniting tensions",
        "link": "https://www.bbc.com/news/articles/cvg57nk373lo?at_medium=RSS&at_campaign=rss",
        "description": "The fresh strikes come after weeks of relative calm in the restive border region between the two countries.",
        "pubDate": "2026-06-10T10:26:26Z",
        "source": "bbc.com",
        "image": "https://ichef.bbci.co.uk/ace/standard/240/cpsprodpb/93a5/live/ac2cfa10-64ab-11f1-9c89-85486d952f7c.jpg",
        "bias": 0
      },
      {
        "title": "Who pays for a supersized World Cup?",
        "link": "https://www.aljazeera.com/video/by-the-numbers-3/2026/6/10/who-pays-for-a-supersized-world-cup?traffic_source=rss",
        "description": "The biggest World Cup ever, with 48 teams and 104 matches, is expected to bring a record $13bn for FIFA.",
        "pubDate": "2026-06-10T10:23:33Z",
        "source": "aljazeera.com",
        "image": "",
        "bias": -1
      },
      {
        "title": "Graham Platner wins Maine primary election: Results and key takeaways",
        "link": "https://www.aljazeera.com/news/2026/6/10/graham-platner-wins-maine-primary-election-results-and-key-takeaways?traffic_source=rss",
        "description": "Platner wins in Maine, Republican Nancy Mace loses in S Carolina. Results for Nevada and North Carolina also announced.",
        "pubDate": "2026-06-10T10:22:43Z",
        "source": "aljazeera.com",
        "image": "",
        "bias": -1
      },
      {
        "title": "Taiwan fires rockets in China’s direction from a US-supplied mobile launching system in drill - AP News",
        "link": "https://news.google.com/rss/articles/CBMipwFBVV95cUxPY1hRU2lHMnhPTmI1YUhYOU9lOXVGNDhucklYanpmM3pVVHJpZnRMcndmX0p0cThyejYtTDZRSnFJWUhDZVQ2TXR4Z1djWkc3eklwQXM0ajUwS3Rld1NqSlFrNFlDUTBXTi15bTVjQXphQXM0Z1d5Q3poaXhlV1BBY3NGOUtEQ0NMRVBNeEhXYmFjdS1HSlhjd0xrZHRKS0VXaWtTaGZpWQ?oc=5",
        "description": "",
        "pubDate": "2026-06-10T10:15:00Z",
        "source": "news.google.com",
        "image": "",
        "bias": 0
      },
      {
        "title": "UK leaders call for calm as protests break out after Belfast street stabbing - AP News",
        "link": "https://news.google.com/rss/articles/CBMimAFBVV95cUxNYlFMNGRoQ1ZJMTBlSHNSeDZwTlp0LVQ1QWZfYzY5anRoY1VMdDJhb1BWMTdlLXpmZ001OUowZVZSNXRfT0lqS2RzaV9xazVvZjlhcVhxRWF3OUlTbW1pdVJlSWNHZ0IzSEJtemZDWm5sMW0xMjN2MkprYlJkMW5xckM3b0lJa3U2cm1sZ2tqd3RxQVozc294aw?oc=5",
        "description": "",
        "pubDate": "2026-06-10T10:13:00Z",
        "source": "news.google.com",
        "image": "",
        "bias": 0
      },
      {
        "title": "A four-year-old’s recovery from the trauma of war in Lebanon",
        "link": "https://www.aljazeera.com/video/newsfeed/2026/6/10/a-four-year-olds-recovery-from-the-trauma-of-war-in-lebanon?traffic_source=rss",
        "description": "Four-year-old Malika was seriously wounded in an Israeli attack that killed her mother.",
        "pubDate": "2026-06-10T10:09:41Z",
        "source": "aljazeera.com",
        "image": "",
        "bias": -1
      },
      {
        "title": "Why is the FIFA World Cup 2026 being held in three countries?",
        "link": "https://www.aljazeera.com/sports/2026/6/10/why-is-the-fifa-world-cup-2026-being-held-in-three-countries?traffic_source=rss",
        "description": "The 2026 World Cup is the first to be held in three different host nations - but why? Al Jazeera explains.",
        "pubDate": "2026-06-10T09:57:57Z",
        "source": "aljazeera.com",
        "image": "",
        "bias": -1
      },
      {
        "title": "Zelensky under pressure to end row with Poland over WW2 name of army unit",
        "link": "https://www.bbc.com/news/articles/c992r4kn5j9o?at_medium=RSS&at_campaign=rss",
        "description": "Poland is threatening to strip Ukraine's president of a state honour over the naming Ukrainian military unit after controversial World War Two fighters.",
        "pubDate": "2026-06-10T09:57:20Z",
        "source": "bbc.com",
        "image": "https://ichef.bbci.co.uk/ace/standard/240/cpsprodpb/2043/live/875c77e0-64ad-11f1-b1db-af71d47507d6.jpg",
        "bias": 0
      },
      {
        "title": "World Cup referee denied US entry arrives home to hero's welcome in Somalia",
        "link": "https://www.bbc.com/sport/football/articles/c2dylj8kj82o?at_medium=RSS&at_campaign=rss",
        "description": "Omar Artan vows to officiate at the 2030 tournament instead, following his ban from entering the US.",
        "pubDate": "2026-06-10T09:50:32Z",
        "source": "bbc.com",
        "image": "https://ichef.bbci.co.uk/ace/standard/240/cpsprodpb/c13f/live/e4085170-64b3-11f1-8e1d-bbbb1017d210.jpg",
        "bias": 0
      },
      {
        "title": "Iran fires missiles at US bases carrying images of killed commanders",
        "link": "https://www.aljazeera.com/video/newsfeed/2026/6/10/iran-fires-missiles-at-us-bases-carrying-images-of-killed-commanders?traffic_source=rss",
        "description": "Iranian state media released video showing the launch of missiles towards US bases in the Middle East.",
        "pubDate": "2026-06-10T09:45:33Z",
        "source": "aljazeera.com",
        "image": "",
        "bias": -1
      },
      {
        "title": "Ukraine launches long-range strikes on military and energy sites in Russia - AP News",
        "link": "https://news.google.com/rss/articles/CBMimwFBVV95cUxPWHRqb3c5OS1la0dWUGJTbFBDSzg0TU1NOUc1R0ttQ3BXeFIyQmdJdExnQW4tQkUyenlwdklzRHo4ZGNhT3hvVjVDM0dOLU0tSUtFdloxWXFreTA1c0tSVEcwbHY4XzFYT2dZTEJkVkFCbnM4SmZpVnUyNld0SFJjRGhTOXUtcWlzTlRaSGpjM2RRYlY4RjgtU1FHUQ?oc=5",
        "description": "",
        "pubDate": "2026-06-10T09:43:00Z",
        "source": "news.google.com",
        "image": "",
        "bias": 0
      },
      {
        "title": "India’s Bengal pushes out Muslim Bangladeshis, deepening religious tensions",
        "link": "https://www.aljazeera.com/news/2026/6/10/indias-bengal-pushes-out-muslim-bangladeshis-deepening-religious-tensions?traffic_source=rss",
        "description": "Hundreds 'pushed' to border and many others put in detention centres as part of a crackdown on undocumented migrants.",
        "pubDate": "2026-06-10T09:22:53Z",
        "source": "aljazeera.com",
        "image": "",
        "bias": -1
      },
      {
        "title": "A street in The Hague is drenched in orange as Netherlands soccer fans celebrate the World Cup - AP News",
        "link": "https://news.google.com/rss/articles/CBMiogFBVV95cUxNcHp2SWcyR25qM3V4WmxENjdVMDFsT0dzQWdFU1gzblZJUTVfQUYzS0hRbkZhR3NvTmpiVE5iVXdDQUZUNVZGaTFnUGozNFQ4ejV6dk91SXdaX1VjQW91NjRGVkNka3BDZEpXeGp1MkV3dER2VlM5S2Zod2VOMGJjYVB3VFF6OU53WnZiVFpSS3c2Qy1HQmZ6emlUVjF4d1N1QXc?oc=5",
        "description": "",
        "pubDate": "2026-06-10T09:07:58Z",
        "source": "news.google.com",
        "image": "",
        "bias": 0
      },
      {
        "title": "Argentina World Cup 2026 preview: Players to watch, group matches and squad",
        "link": "https://www.aljazeera.com/sports/2026/6/10/argentina-world-cup-2026-preview-players-to-watch-group-matches-squad?traffic_source=rss",
        "description": "Messi is hoping to overcome injury to help Argentina become the first back-to-back World Cup champions since 1962.",
        "pubDate": "2026-06-10T08:59:58Z",
        "source": "aljazeera.com",
        "image": "",
        "bias": -1
      },
      {
        "title": "Israel is tightening its grip on east Jerusalem with evictions and demolitions - AP News",
        "link": "https://news.google.com/rss/articles/CBMiugFBVV95cUxQU3dZSDJacGdrb04tZVQyOTR4ZnpOY0l0NGZ0MjBxUHd2QXV2VGVod0Qyb0stcXBKbWtKQ0VtX2hSdVlsLXZKLXJ0aC12ZTc1WVNUM0Z4OUo5cFYwVE5EUVB1cHA4WU1jc3hZQXRHaDBLYlNoTHh1ZHdnd3d3UE5Mb1VLSXlJY3NuWUdIeEltb25vY3JoQXNFSEVTQ1VNRFROY1lTRFN5Vk5Xdk9hMjdPLW5hY1BKcWpfMkE?oc=5",
        "description": "",
        "pubDate": "2026-06-10T08:48:00Z",
        "source": "news.google.com",
        "image": "",
        "bias": 0
      },
      {
        "title": "China and North Korea renew ties, complicating U.S. response to Kim's nuclear program",
        "link": "https://www.npr.org/2026/06/10/nx-s1-5851837/china-and-north-korea-renew-ties-complicating-u-s-response-to-kims-nuclear-program",
        "description": "With Xi Jinping and Kim Jong Un reaffirming ties while sidestepping nuclear tensions, the U.S. faces a growing challenge in responding to an increasingly confident, nuclear-armed North Korea.",
        "pubDate": "2026-06-10T08:42:39Z",
        "source": "npr.org",
        "image": "",
        "bias": -1
      },
      {
        "title": "World shares are mostly lower after a tech sell-off on Wall Street, while oil prices waver - AP News",
        "link": "https://news.google.com/rss/articles/CBMilAFBVV95cUxOTk56ZkgzR0tyRzhaSUtXODBPMWtIdW04WUNsWXljTkhDM1F1V29aOXFNbFlndXZRYzV3blU3MkJEdHlyeHh3b09sVGp2dDVaVF9YNkVJczAxSXdQaEwzcDRIMl9HLVdqbVpQV2ZfOHJMbmRHU2RUbk5WNHM5SUh0cXBOdVpxelVrSzZ0ZVlENWZMa2Vo?oc=5",
        "description": "",
        "pubDate": "2026-06-10T08:42:00Z",
        "source": "news.google.com",
        "image": "",
        "bias": 0
      },
      {
        "title": "Israeli leader who pulled out of Lebanon warns against getting stuck again",
        "link": "https://www.npr.org/2026/06/10/g-s1-126791/israeli-leader-who-pulled-out-of-lebanon-warns-against-getting-stuck-again",
        "description": "Ehud Barak withdrew Israeli forces from Lebanon in 2000, ending an occupation that lasted nearly two decades. He says that was a quagmire Israel shouldn't repeat.",
        "pubDate": "2026-06-10T08:40:59Z",
        "source": "npr.org",
        "image": "",
        "bias": -1
      },
      {
        "title": "In Ukraine, a competition puts soldiers' drone skills to the test",
        "link": "https://www.npr.org/2026/06/10/nx-s1-5847603/in-ukraine-a-competition-puts-soldiers-drone-skills-to-the-test",
        "description": "As drones become the weapon of choice in the Russia-Ukraine war, a group of soldiers test their skills in an unusual competition.",
        "pubDate": "2026-06-10T08:39:50Z",
        "source": "npr.org",
        "image": "",
        "bias": -1
      },
      {
        "title": "Anti-immigration protests break out in Belfast after knife attack",
        "link": "https://www.aljazeera.com/gallery/2026/6/10/anti-immigration-protests-break-out-in-belfast-after-knife-attack?traffic_source=rss",
        "description": "Northern Ireland’s political leaders call for calm after a knife attack led to anti-immigration protests in the capital.",
        "pubDate": "2026-06-10T08:30:15Z",
        "source": "aljazeera.com",
        "image": "",
        "bias": -1
      },
      {
        "title": "Rising from the rubble: A Gaza tech incubator defies Israel’s war",
        "link": "https://www.aljazeera.com/economy/2026/6/10/rising-from-the-rubble-a-gaza-tech-incubator-defies-israels-war?traffic_source=rss",
        "description": "Israel's war on Gaza has decimated the tech sector, killing experts and destroying incubators that offered opportunity.",
        "pubDate": "2026-06-10T08:27:28Z",
        "source": "aljazeera.com",
        "image": "",
        "bias": -1
      },
      {
        "title": "Spidercam crashes onto pitch during Hungary match",
        "link": "https://www.aljazeera.com/video/newsfeed/2026/6/10/spidercam-crashes-onto-pitch-during-hungary-match?traffic_source=rss",
        "description": "A spider camera crashed near the touchline during a football friendly between Hungary and Kazakhstan.",
        "pubDate": "2026-06-10T08:19:48Z",
        "source": "aljazeera.com",
        "image": "",
        "bias": -1
      },
      {
        "title": "Twelve killed in Johannesburg mass shooting, manhunt under way",
        "link": "https://www.aljazeera.com/news/2026/6/10/twelve-killed-in-johannesburg-mass-shooting-manhunt-under-way?traffic_source=rss",
        "description": "Police say a manhunt is under way for more than 10 suspects after the attack on an informal settlement.",
        "pubDate": "2026-06-10T08:11:07Z",
        "source": "aljazeera.com",
        "image": "",
        "bias": -1
      },
      {
        "title": "China car exports jump 73% in May as high fuel prices raise interest in EVs - AP News",
        "link": "https://news.google.com/rss/articles/CBMikgFBVV95cUxPZ2dKZEZNTHVzdVd4cDF0dllpUmRZcWZmZ1ZqcGE2Ny1xVlc5dWh1R3k2OWY4QUhBejBka0E4WmFxSVlpdjQ5Mjl2c2JPRGxvSkZRcGQ2Y1VCbWF2aVl0d3pDVnVwT3hrQ09Qc2xzbFNiNHVTMDdjcHk2bUltQ3M5UDg2eXRqaldUdUJiSmNobHRCZw?oc=5",
        "description": "",
        "pubDate": "2026-06-10T07:48:00Z",
        "source": "news.google.com",
        "image": "",
        "bias": 0
      }
    ],
    "Politics": [
      {
        "title": "Starmer dithering over defence spending, says Badenoch",
        "link": "https://www.bbc.com/news/articles/ckg4rknndjeo?at_medium=RSS&at_campaign=rss",
        "description": "The clash at PMQs comes amid a cabinet battle over how a military investment plan will be funded.",
        "pubDate": "2026-06-10T13:25:12Z",
        "source": "bbc.com",
        "image": "https://ichef.bbci.co.uk/ace/standard/240/cpsprodpb/24e1/live/d4766170-64cc-11f1-8e1d-bbbb1017d210.jpg",
        "bias": 0
      },
      {
        "title": "US strikes Iran and Tehran fires back. Trump says Iran will ‘pay the price’ for stalled talks - AP News",
        "link": "https://news.google.com/rss/articles/CBMiqwFBVV95cUxPU25kWmtrYVNpdHBud0dxUDhZdUx0OFMyQUxOWER5cXowaW8zWk9pdWNBeWdycUNTTXp4VjlmSWF1UDRzOEpBdl9RRTlYeno2cXBHUEJuVDJaTk05dldzaEwza29fR2I1NmpsZU5JZUlUWjNoWlZUTXFiaFFLYm9oSHR5Ukk4X2s5X193eU5fVm5KWjZmSHBsTnJ2U29JU1lVb3ZtLUZuTUpDNHM?oc=5",
        "description": "",
        "pubDate": "2026-06-10T12:37:00Z",
        "source": "news.google.com",
        "image": "",
        "bias": 0
      },
      {
        "title": "Fly-tippers should face higher fines, Reform UK urges",
        "link": "https://www.bbc.com/news/articles/cx26lp88j75o?at_medium=RSS&at_campaign=rss",
        "description": "The party also wants an annual \"national action day\" to help \"rekindle civic pride\".",
        "pubDate": "2026-06-10T12:04:30Z",
        "source": "bbc.com",
        "image": "https://ichef.bbci.co.uk/ace/standard/240/cpsprodpb/a2ea/live/3efe3da0-64ba-11f1-8546-8f19e4fe30f4.jpg",
        "bias": 0
      },
      {
        "title": "A Thai woman is in custody after an American diplomat was found dead in Myanmar - AP News",
        "link": "https://news.google.com/rss/articles/CBMilgFBVV95cUxNVk8xZWVtVFBLMllfX3E0MjJxcUFSeWhXZl9hTm5SMkFWR0tuLUt2ZXgyWVpzWkcwdlZuQWM2UlJ6RWpQUEdBeUZGRWd6NENyUk03bERvRFVwSUJVQWZ1Z1NORUg3TFUtTm8wU2pFYkZsUTFhYjVBaHdWR0YxOEJJZDBwTkpMcTUtRWlNcmFZLVRLdDJRSFE?oc=5",
        "description": "",
        "pubDate": "2026-06-10T11:02:00Z",
        "source": "news.google.com",
        "image": "",
        "bias": 0
      },
      {
        "title": "A Pentagon list overhaul puts Mormon church’s Christian identity back in the spotlight - AP News",
        "link": "https://news.google.com/rss/articles/CBMirgFBVV95cUxOcy01dGtLTFpBMXdWQW1wWHk5c2pNNGE3U0FkbmxYMzhHSUNzNlRsUk9FM09scjh3bDBudDRnOU1qRTVDODdTeWUxZ0M0SXp3cDJQQXF2NmU5UXNsLVlrbmoydVIzeDNjRUhEaU9vY2N5YzgxMXBpakJyVUpfVmdtVGdLMUZpb0d0dVVKemZLcGZEVFZyR1diWGlKa3VKNjZYRjBEa0lUMjhhTm9WX0E?oc=5",
        "description": "",
        "pubDate": "2026-06-10T11:00:00Z",
        "source": "news.google.com",
        "image": "",
        "bias": 0
      },
      {
        "title": "Bill Gates will testify in a congressional panel’s Jeffrey Epstein investigation - AP News",
        "link": "https://news.google.com/rss/articles/CBMiqgFBVV95cUxObVlSeHBqNi1fUVVuMGdrZWZiRGtnd19IbU5hSmVHUDVkZTdhNk1xYWpjN3VrNzBCdVlSUVJCSkhXeWpxMFhDc2s0ZFZaMkJiUGZ2dkVJeGZtUlJQbUJhYVAzaFpNYTVydjVGaXg0dEoza2xNeExLR0ExemZJNzhBN24ySlp5NTI5cXpMS0FObnE0NzBpYWwxNGcxdGZ6bGR1cXgwYk1JUGJzUQ?oc=5",
        "description": "",
        "pubDate": "2026-06-10T10:49:00Z",
        "source": "news.google.com",
        "image": "",
        "bias": 0
      },
      {
        "title": "SpaceX wants regular investors to help its stock launch. Here's what to know before clicking 'buy' - AP News",
        "link": "https://news.google.com/rss/articles/CBMiqwFBVV95cUxPUlNKdTFPaVlBOWp0TVd5MHYxY3BobnBuODhJWVdrVTVoY1JYVXdaRUFwNVBXRElpa3QxQ2JXdDNpZVJmaXVsMnVVSE1sOHZVemJ4SkdlcnJ2RE5HblpKZFhMOVhSRGFoeGx2UVZ5aEpUdy1DM0dscWctRHZzY2xDRXZDeC00UXpSeWQ3TTdVSGhFcWhPNlRGRkZiM0lDUmpwcUM0RjVQbjJUa2M?oc=5",
        "description": "",
        "pubDate": "2026-06-10T10:37:00Z",
        "source": "news.google.com",
        "image": "",
        "bias": 0
      },
      {
        "title": "Edmunds’ five best used performance cars for less than $25,000 - AP News",
        "link": "https://news.google.com/rss/articles/CBMilgFBVV95cUxPazNVeW42MjdHMjhWR2xjYWhtSi15N0Z0SE9yb1BJYmRRUWRQWEwyRHZmRDB2SFNmMmEwVENfUkQ1aFpOSk9PaTlvVl9zRkRuRzc3eDctQ2xybURrSzROczdLLThxMEJQOXEwNElaNlR1blNSSkhmUzRESnlqS21jUGw2MXQyNGVYbmVXbjlJUmRmTVU4TUE?oc=5",
        "description": "",
        "pubDate": "2026-06-10T10:28:27Z",
        "source": "news.google.com",
        "image": "",
        "bias": 0
      },
      {
        "title": "Amnesty accuses Israel's government of 'ethnic cleansing' of Palestinians from the West Bank - AP News",
        "link": "https://news.google.com/rss/articles/CBMitAFBVV95cUxNMW1CMzk5U01xTzVLM2wtcE5GbnI1QjNrazlkTWM2ejVkLW5Cb0ozLVdTY2ItZHBfV0N6QllqaG5IS2RpTFlnRU9jeUZsYk55MmFxSXAzLXh0NnpNZnB3X3RGeDlqWXBjSHFSOWZERHIya1BmWF85UUs2Qmpya1MxT1hDVnhTOWU4WHl3ZkJpc2J1NHI5eTMwVXdHdlp0aEh5ZzFoTmpYbnFsbGJvcEQwYmhfXzE?oc=5",
        "description": "",
        "pubDate": "2026-06-10T10:19:00Z",
        "source": "news.google.com",
        "image": "",
        "bias": 0
      },
      {
        "title": "ICE denies having a protester database. But a letter to Congress sheds more light",
        "link": "https://www.npr.org/2026/06/10/nx-s1-5843159/ice-protester-database-dhs",
        "description": "In a previously unpublicized letter to Congress, the newly-departed head of ICE said the agency collects data on people suspected of potentially unlawful activity, which could include protesters.",
        "pubDate": "2026-06-10T10:00:00Z",
        "source": "npr.org",
        "image": "",
        "bias": -1
      },
      {
        "title": "San Francisco immigration court shuts down, striking at heart of historic advocacy",
        "link": "https://www.npr.org/2026/06/10/g-s1-126345/san-franciso-court-immigration-closure-asylum-layoffs",
        "description": "The main San Francisco court was one of the busiest in the country, hearing thousands of cases a year. It was also one of the courts most likely to grant an immigrants' asylum application.",
        "pubDate": "2026-06-10T09:00:00Z",
        "source": "npr.org",
        "image": "",
        "bias": -1
      },
      {
        "title": "Bill Gates is appearing before Congress over Epstein involvement",
        "link": "https://www.npr.org/2026/06/10/nx-s1-5851609/bill-gates-jeffrey-epstein-files-congress-pam-bondi",
        "description": "Gates will sit for a closed-door interview before the House Oversight Committee about his relationship with convicted sex offender Jeffrey Epstein.",
        "pubDate": "2026-06-10T09:00:00Z",
        "source": "npr.org",
        "image": "",
        "bias": -1
      },
      {
        "title": "House Republicans pass bill to fund ICE and Border Patrol",
        "link": "https://www.npr.org/2026/06/10/nx-s1-5851665/house-republicans-pass-bill-to-fund-ice-and-border-patrol",
        "description": "House Republicans have passed roughly $70 billion in funding for immigration enforcement. The package funds ICE and Border Patrol through the remainder of President Trump's term.",
        "pubDate": "2026-06-10T08:40:05Z",
        "source": "npr.org",
        "image": "",
        "bias": -1
      },
      {
        "title": "Rep. James Walkinshaw on funding for ICE and the future of immigration enforcement",
        "link": "https://www.npr.org/2026/06/10/nx-s1-5852226/rep-james-walkinshaw-on-funding-for-ice-and-the-future-of-immigration-enforcement",
        "description": "Congress has passed funding for ICE and Border Patrol through the rest of President Trump's second term. NPR's Michel Martin speaks with Democratic Rep. James Walkinshaw of Virginia.",
        "pubDate": "2026-06-10T08:39:59Z",
        "source": "npr.org",
        "image": "",
        "bias": -1
      },
      {
        "title": "Police are investigating a large burning cross at a Chicago park - AP News",
        "link": "https://news.google.com/rss/articles/CBMingFBVV95cUxQRGRpOXZiTnl3bklDVXVtMUN0UTk2Ul8yUWx1bTUzdk1zenB3QXRyTXBVYlQwQU9MOGFZZEN4X1JKQ0F6R2h5MlN5TTRrdlkwYnVpTU9FZ2s1UUhmVndmcDQ5bm50eG5MbmdpcTNPa2VadVUyb3J6V1l4dTJRZjFDd0dRRUpNVy1VdHFBaExNXzRiVVpiTnhkWTBUZWxNdw?oc=5",
        "description": "",
        "pubDate": "2026-06-10T06:26:00Z",
        "source": "news.google.com",
        "image": "",
        "bias": 0
      },
      {
        "title": "Illegal mini-marts to shut for up to 12 months under law change prompted by BBC",
        "link": "https://www.bbc.com/news/articles/cqj1rkqqrgro?at_medium=RSS&at_campaign=rss",
        "description": "Under current rules, shops breaking the law can only be closed for up to six months in England and Wales.",
        "pubDate": "2026-06-10T04:17:02Z",
        "source": "bbc.com",
        "image": "https://ichef.bbci.co.uk/ace/standard/240/cpsprodpb/8084/live/8a0ee320-64ac-11f1-8e1d-bbbb1017d210.jpg",
        "bias": 0
      },
      {
        "title": "Law firms cheated in filing claims with NFL's $1 billion concussion settlement fund, report says - AP News",
        "link": "https://news.google.com/rss/articles/CBMinAFBVV95cUxNbmxESGJzUlYxRVdxOU5sbzBFQlMwZzJ0eFBHRG9qbnd4dFdwRURPbU93cmd3Y0ljTTdWTGt3SWJ0MFZKU1ZSQThHdmY1UTNlaUVMY1pWcDkwUDRlcHNnSnE0aDZ2RFFqWmJfZ3ZTdzdldHRCQW1YeDI5QVpmVE9waFJ6cVppWjV0T3cwR25uZjFOdkZCUnlDVFIwc3c?oc=5",
        "description": "",
        "pubDate": "2026-06-10T04:09:00Z",
        "source": "news.google.com",
        "image": "",
        "bias": 0
      },
      {
        "title": "In Nevada, Trump's policies are making things tough for Republican Gov. Joe Lombardo",
        "link": "https://www.npr.org/2026/06/10/nx-s1-5850242/trump-nevada-results-lombardo-ford-governor",
        "description": "In one of the most competitive races for governor this year, Nevada Democratic Attorney General Aaron Ford will challenge Republican Gov. Joe Lomardo for his office in November.",
        "pubDate": "2026-06-10T04:08:07Z",
        "source": "npr.org",
        "image": "",
        "bias": -1
      },
      {
        "title": "Judge bars Alabama nitrogen gas execution, says method is unconstitutionally cruel - AP News",
        "link": "https://news.google.com/rss/articles/CBMiogFBVV95cUxNYm5fVUNZT2xLTEJOUDA2M2REbGExMlFTdGhmSGwtWDZURDZDSmdQb3FaMFVnZ2ZPNGZGQjJkUXU4a0FEYjVQWkRzOVpSU0NiSkk2cVV3aFJfNkVOTlIwM0J3OEdfWFZLYXl4aTNlR0pDLUVGZHRUNFotSUZyZjA4OTRQTVhub1IwMExfWGU1eUJhbU5XUzBBYU42cmpMVEh2dlE?oc=5",
        "description": "",
        "pubDate": "2026-06-10T02:02:00Z",
        "source": "news.google.com",
        "image": "",
        "bias": 0
      },
      {
        "title": "Evette, backed by Trump, and Wilson, a Trump supporter, head to S.C. governor runoff",
        "link": "https://www.npr.org/2026/06/09/nx-s1-5851591/trump-south-carolina-evette-wilson-governor",
        "description": "In South Carolina, both Republican candidates for governor are MAGA devotees, but Trump only endorsed Lt. Gov. Pamela Evette, not Attorney General Alan Wilson. The two are headed to a GOP runoff.",
        "pubDate": "2026-06-10T01:21:27Z",
        "source": "npr.org",
        "image": "",
        "bias": -1
      }
    ],
    "Tech": [
      {
        "title": "Maine Primary Results 2026: Senate, House and Governor - AP News",
        "link": "https://news.google.com/rss/articles/CBMic0FVX3lxTE1mLVA2MFB6QXFlSkIwc3JLa2VxWTI0UXNETXZFZ1IydzJ4ZDZSOVpzaWY2Y3dDRXRKNERxc2pYUVVISmtkUmdHVUdRZm5NQzRLdko2Z1RpN2ZabFh2dUlSZHliV1U1OVVGTjlXbE1hQXRKSFE?oc=5",
        "description": "",
        "pubDate": "2026-06-10T12:50:23Z",
        "source": "news.google.com",
        "image": "",
        "bias": 0
      },
      {
        "title": "A wild Stanley Cup Final swings again as Hurricanes win 5-3 to make series 2-2 with Golden Knights - AP News",
        "link": "https://news.google.com/rss/articles/CBMipgFBVV95cUxQX091U3dqaDZuTDlaWkRRanA0UkE0NHRuaG12Wm1VXzFhMVlTSV9IUGNjUUk0elRkSF9vMVA5N2dEcHFGY20tcDZmSE84aDBPLUUzSnRnT1R5S0NILWhhQk1sZTVDaHg1MjNrTG4yamdQRWVVdldUS1h4M1VyaXdaLW5aX213NGtCOERfWGkweUJKVW81NDhMdnY1QkdVMDJIMFM4WWln?oc=5",
        "description": "",
        "pubDate": "2026-06-10T06:11:00Z",
        "source": "news.google.com",
        "image": "",
        "bias": 0
      },
      {
        "title": "Some burial societies in Africa now focus on helping the living, too - AP News",
        "link": "https://news.google.com/rss/articles/CBMirwFBVV95cUxQSGJKU3VGaWxCWjlpYTJtR0ItYnVyV2JFM2ZpN3ExMUJ1WGFqRmQyNThSMEVkX3JGeFFCelFOdk9DN2JRRmphVDdSY0ZOX0lfRFNJTUNtYWdsMU0ybTBwRldVdHdaeFZLNi16cHdtM21fU0FiZzA3YmxGRXBlb2R0UzE3d0t5OFVFLUxlbkJjZTdaaDduUXZLRW4zc0RoT29Ga0QwWnd1TkRmeE9jeXpR?oc=5",
        "description": "",
        "pubDate": "2026-06-10T04:35:00Z",
        "source": "news.google.com",
        "image": "",
        "bias": 0
      },
      {
        "title": "US Catholic bishops are consecrating the nation to the Sacred Heart of Jesus. Here's what that means - AP News",
        "link": "https://news.google.com/rss/articles/CBMipwFBVV95cUxNQUwtR2tIX3lCMDN2QTlIRGthSUg1a0VteWZmQTV5NkZRQUhoQU04RGstOG5HX3N1cm1YN25pWW1naDIwRVhVZGcyODRCT083NjhaQk9rc0lQaHo3d2VXNHRYaWhwc0R2c1U5STg3eU1jMmVzcFQ3S0dTZWVmZVc2b1BXVVVZeUtqQ3dEd25ucnRLaVJpdEx1T1NndE5ZZmpLQjU0V0kzTQ?oc=5",
        "description": "",
        "pubDate": "2026-06-10T04:02:00Z",
        "source": "news.google.com",
        "image": "",
        "bias": 0
      },
      {
        "title": "2 prominent California congressional races will test Democrats’ redrawn US House map - AP News",
        "link": "https://news.google.com/rss/articles/CBMimAFBVV95cUxPUmFzbTJOOGROZ1RYSXpnRzRBOTh6SGdXV1lGd3BEOTN2UzlQT2lnckM3TWVlZkxxM1RpZE5rMldBOER5Vk5sckNYd3MxYk9wRlRzeFhlSDBlUDYySC1Yc09nNmpMdjNEU3ZYMU1CdUFveDFndzQ4cGhaWjVSRG9sZXNxUFhHbldwY2NrMnlTRHMyS0ExOExheQ?oc=5",
        "description": "",
        "pubDate": "2026-06-10T02:36:00Z",
        "source": "news.google.com",
        "image": "",
        "bias": 0
      }
    ],
    "Science": [
      {
        "title": "Texas teen who fatally stabbed track athlete at school meet found guilty and sentenced to prison - AP News",
        "link": "https://news.google.com/rss/articles/CBMijgFBVV95cUxNUmgtZVRuczhEVHNyYnFvR2ZMcFR3SzFYRlIwT255V29GU1FSX05rSTlYdlBfckhUREFPd2ZxX0prOVlfZUdfQjkxYzZDUEM3YkVpNW5HaEtOczdtQmE3UGR3MS04TW9sRlZzOHktbkFDYVlMdzBOd3VmWUdGQVFpWldDc0c5OTJTZzdNaUpn?oc=5",
        "description": "",
        "pubDate": "2026-06-10T12:47:00Z",
        "source": "news.google.com",
        "image": "",
        "bias": 0
      },
      {
        "title": "Rare tiger cub from litter of four dies",
        "link": "https://www.bbc.com/news/articles/cp8r1mm1mz6o?at_medium=RSS&at_campaign=rss",
        "description": "These Sumatran tigers are the first of this breed to be welcomed at the animal park in Kent.",
        "pubDate": "2026-06-10T08:29:32Z",
        "source": "bbc.com",
        "image": "https://ichef.bbci.co.uk/ace/standard/240/cpsprodpb/8420/live/495ae4e0-649e-11f1-8ace-096e974f6466.jpg",
        "bias": 0
      },
      {
        "title": "Tuesday's takeaways: Platner's big night, Clyburn carries on and Trump's support gets mixed results - AP News",
        "link": "https://news.google.com/rss/articles/CBMimwFBVV95cUxQYmNVcktlWENnRnU3SzRlTkU0aUUxaFg2T0dLTmlmQkZiRTNxeG4xWkxua2dvem5HS3lMX3JkNGU3aklDT3Fhb25qS0JtemxUdmkzeGJDQ2tHN1FUc3AwellQMWwxMkNNeVYtU2dWNXU3ZFhIcjREbUZMaDVycndKSzRiak5xS3RvdFJkTE9vcDlSM05DV1hacHRTbw?oc=5",
        "description": "",
        "pubDate": "2026-06-10T05:57:00Z",
        "source": "news.google.com",
        "image": "",
        "bias": 0
      },
      {
        "title": "'Our nature project has been amazing for wildlife'",
        "link": "https://www.bbc.com/news/articles/cdxpxkpx113o?at_medium=RSS&at_campaign=rss",
        "description": "Residents have spent the past year sowing wildflower meadows and encouraging no mow areas.",
        "pubDate": "2026-06-10T05:26:02Z",
        "source": "bbc.com",
        "image": "https://ichef.bbci.co.uk/ace/standard/240/cpsprodpb/f980/live/94d1ab30-640c-11f1-a17d-bf3062638caa.jpg",
        "bias": 0
      },
      {
        "title": "Women prepare for 'space jobs that don't exist yet'",
        "link": "https://www.bbc.com/news/articles/cy49d000kgwo?at_medium=RSS&at_campaign=rss",
        "description": "Hundreds of women attend the annual AeroWomen women event in Yeovil.",
        "pubDate": "2026-06-10T05:21:06Z",
        "source": "bbc.com",
        "image": "https://ichef.bbci.co.uk/ace/standard/240/cpsprodpb/1803/live/0431e780-6357-11f1-8b15-6100cfbc3083.jpg",
        "bias": 0
      },
      {
        "title": "Hundreds of twitchers flock to see African bird in UK for first time",
        "link": "https://www.bbc.com/news/articles/cd0mz82lvrjo?at_medium=RSS&at_campaign=rss",
        "description": "It is the first time the African bird has been recorded in the UK.",
        "pubDate": "2026-06-10T05:12:24Z",
        "source": "bbc.com",
        "image": "https://ichef.bbci.co.uk/ace/standard/240/cpsprodpb/2e6c/live/abf422b0-649e-11f1-8e1d-bbbb1017d210.jpg",
        "bias": 0
      },
      {
        "title": "Knicks in 6: NY man’s high school yearbook prediction 6 years ago goes viral - AP News",
        "link": "https://news.google.com/rss/articles/CBMipgFBVV95cUxNdml2Wk5PY3g4QnVaLUo0RHJGVzNhZVZ3VW0zVTFXdll0UWNOMzc5OWxlc1ExbzNGdHM0azdqQXE3UEY3cndzLTlkV0gxemNOZ05yRTVpSmZOZUxNbmZXa3FfTVlHRVRzV3VCUDZlVVExeHB6ZTJsZ3Fza2hlSGVra2hLMUIzTHloQnFLdEJERmx5SnNMUEpjQTZaNmFFZGdFa2wyTW9n?oc=5",
        "description": "",
        "pubDate": "2026-06-10T02:07:00Z",
        "source": "news.google.com",
        "image": "",
        "bias": 0
      },
      {
        "title": "'Synthetic performers' in ads must be identified as AI as new New York law takes effect - AP News",
        "link": "https://news.google.com/rss/articles/CBMipgFBVV95cUxNMGMtdDdSZE9QWnk2Mkt1TGwxQ0hGRWRfMUlXLXRNZTlyQVRBYk5jRjlhaG1acWpjaGZuNHVBc05EVkgtUWxWSWI1SWZxNXVIbnJSSWJ0THRfb09fVDdzMUNsRWxCaEZDVklodWNIMngxYnZha3d2dGM0TTdoQkNaeURnM1BmX3A5cXdnNjM0S29GR0VNYjJFR3FNN01GVmJvZWZ4RkJ3?oc=5",
        "description": "",
        "pubDate": "2026-06-10T00:12:00Z",
        "source": "news.google.com",
        "image": "",
        "bias": 0
      }
    ],
    "Business": [
      {
        "title": "US inflation surges to three-year high of 4.2%",
        "link": "https://www.bbc.com/news/articles/c0myzxjkw99o?at_medium=RSS&at_campaign=rss",
        "description": "Consumers are increasingly feeling the strain of the US Israel war in Iran.",
        "pubDate": "2026-06-10T13:54:56Z",
        "source": "bbc.com",
        "image": "https://ichef.bbci.co.uk/ace/standard/240/cpsprodpb/0c69/live/f9097760-64c8-11f1-8f51-b550443b533b.jpg",
        "bias": 0
      },
      {
        "title": "Inflation tops 4% for the first time in 3 years on spike in gasoline prices",
        "link": "https://www.npr.org/2026/06/10/nx-s1-5853077/inflation-over-4-cpi-gasoline-prices",
        "description": "Inflation has surged to its highest level in more than three years since the U.S. and Israel launched their war on Iran, triggering a surge in gasoline prices.",
        "pubDate": "2026-06-10T13:08:58Z",
        "source": "npr.org",
        "image": "",
        "bias": -1
      },
      {
        "title": "Debenhams boss on the daily habit he swears by",
        "link": "https://www.bbc.com/news/videos/c9d2lxeg3xjo?at_medium=RSS&at_campaign=rss",
        "description": "Dan Finley has overseen the successful turnaround of Debenhams department store. He shares the best advice he's received and some of the keys to his success.",
        "pubDate": "2026-06-10T10:20:20Z",
        "source": "bbc.com",
        "image": "https://ichef.bbci.co.uk/ace/standard/240/cpsprodpb/40e4/live/fa9cc390-64b2-11f1-b1db-af71d47507d6.jpg",
        "bias": 0
      },
      {
        "title": "UK pint prices up 36% since last World Cup – here's why",
        "link": "https://www.bbc.com/news/articles/c982107drq8o?at_medium=RSS&at_campaign=rss",
        "description": "UK pint prices are up 36% since the last World Cup. We look at why beer now costs so much more.",
        "pubDate": "2026-06-10T05:23:36Z",
        "source": "bbc.com",
        "image": "https://ichef.bbci.co.uk/ace/standard/240/cpsprodpb/e77e/live/521557a0-63ef-11f1-97a1-1f201aaa0cb9.jpg",
        "bias": 0
      }
    ],
    "Culture": [
      {
        "title": "BBC cancels Doctor Who Christmas special and Russell T Davies announces exit",
        "link": "https://www.bbc.com/news/articles/c621ln7vx7qo?at_medium=RSS&at_campaign=rss",
        "description": "The BBC said the decision was made \"after careful consideration\" and had \"not been taken lightly\".",
        "pubDate": "2026-06-10T11:43:14Z",
        "source": "bbc.com",
        "image": "https://ichef.bbci.co.uk/ace/standard/240/cpsprodpb/614e/live/fe532290-64b7-11f1-bedc-d9888df33c20.jpg",
        "bias": 0
      },
      {
        "title": "From bands to bags to beer bins - everything you need to know ahead of Download festival",
        "link": "https://www.bbc.com/news/articles/c2e22venmy7o?at_medium=RSS&at_campaign=rss",
        "description": "Donington Park is gearing up to host the UK's biggest festival of rock and metal music.",
        "pubDate": "2026-06-10T05:18:58Z",
        "source": "bbc.com",
        "image": "https://ichef.bbci.co.uk/ace/standard/240/cpsprodpb/798a/live/4336f250-2cb2-11ef-af93-b7f65a764945.png",
        "bias": 0
      }
    ]
  }
}